{"btcinr":{"base_unit":"btc","quote_unit":"inr","low":"2850000.0","high":"3245030.0","last":"3150257.0","type":"SPOT","open":3037551.0,"volume":"380.0023","sell":"3156730.0","buy":"3150572.0","at":1610163733,"name":"BTC/INR"},"xrpinr":{"base_unit":"xrp","quote_unit":"inr","low":"22.6","high":"27.7","last":"25.15","type":"SPOT","open":23.95,"volume":"5564918.0","sell":"25.1475","buy":"25.051","at":1610163733,"name":"XRP/INR"},"ethinr":{"base_unit":"eth","quote_unit":"inr","low":"89555.9","high":"97700.2","last":"95800.0","type":"SPOT","open":91507.1,"volume":"2970.702","sell":"95797.8","buy":"95650.0","at":1610163733,"name":"ETH/INR"},"trxinr":{"base_unit":"trx","quote_unit":"inr","low":"2.3167","high":"2.4001","last":"2.4001","type":"SPOT","open":2.3307,"volume":"14427474.0","sell":"2.4003","buy":"2.4001","at":1610163733,"name":"TRX/INR"},"eosinr":{"base_unit":"eos","quote_unit":"inr","low":"235.0","high":"250.0","last":"244.0","type":"SPOT","open":239.9,"volume":"10780.41","sell":"244.98","buy":"244.0","at":1610163733,"name":"EOS/INR"},"zilinr":{"base_unit":"zil","quote_unit":"inr","low":"5.5","high":"5.95","last":"5.75","type":"SPOT","open":5.5,"volume":"2919.0","sell":"5.94","buy":"5.63","at":1610163733,"name":"ZIL/INR"},"batinr":{"base_unit":"bat","quote_unit":"inr","low":"19.001","high":"20.998","last":"19.501","type":"SPOT","open":19.49,"volume":"204430.86","sell":"19.8","buy":"19.5","at":1610163733,"name":"BAT/INR"},"usdtinr":{"base_unit":"usdt","quote_unit":"inr","low":"76.8","high":"78.9","last":"78.33","type":"SPOT","open":78.53,"volume":"5723252.31","sell":"78.33","buy":"78.13","at":1610163733,"name":"USDT/INR"},"wrxinr":{"base_unit":"wrx","quote_unit":"inr","low":"6.21","high":"6.99","last":"6.44","type":"SPOT","open":6.38,"volume":"2076075.0","sell":"6.44","buy":"6.41","at":1610163733,"name":"WRX/INR"},"maticinr":{"base_unit":"matic","quote_unit":"inr","low":"2.3","high":"2.65","last":"2.496","type":"SPOT","open":2.368,"volume":"6776066.0","sell":"2.499","buy":"2.483","at":1610163733,"name":"MATIC/INR"},"bchinr":{"base_unit":"bch","quote_unit":"inr","low":"33000.0","high":"35499.0","last":"34100.0","type":"SPOT","open":33600.0,"volume":"219.807","sell":"34195.0","buy":"34000.0","at":1610163733,"name":"BCH/INR"},"bnbinr":{"base_unit":"bnb","quote_unit":"inr","low":"3240.0","high":"3369.0","last":"3351.32","type":"SPOT","open":3257.0,"volume":"870.7101","sell":"3356.29","buy":"3351.32","at":1610163733,"name":"BNB/INR"},"bttinr":{"base_unit":"btt","quote_unit":"inr","low":"0.02525","high":"0.04199","last":"0.03436","type":"SPOT","open":0.0258,"volume":"425875095.0","sell":"0.03436","buy":"0.03435","at":1610163733,"name":"BTT/INR"},"chzinr":{"base_unit":"chz","quote_unit":"inr","low":"1.999","high":"1.999","last":"1.999","type":"SPOT","open":1.999,"volume":"0.0","sell":"1.991","buy":"1.301","at":1610163733,"name":"CHZ/INR"},"oneinr":{"base_unit":"one","quote_unit":"inr","low":"0.47","high":"0.52","last":"0.52","type":"SPOT","open":0.48,"volume":"76286.0","sell":"0.6","buy":"0.43","at":1610163733,"name":"ONE/INR"},"yfiinr":{"base_unit":"yfi","quote_unit":"inr","low":"2260000.0","high":"2980739.0","last":"2826218.0","type":"SPOT","open":2325767.0,"volume":"34.28622","sell":"2827151.0","buy":"2826218.0","at":1610163733,"name":"YFI/INR"},"uniinr":{"base_unit":"uni","quote_unit":"inr","low":"445.0","high":"490.0","last":"476.0","type":"SPOT","open":474.75,"volume":"20565.24","sell":"476.0","buy":"475.5","at":1610163733,"name":"UNI/INR"},"linkinr":{"base_unit":"link","quote_unit":"inr","low":"1151.51","high":"1254.99","last":"1235.0","type":"SPOT","open":1194.99,"volume":"4648.3","sell":"1235.0","buy":"1230.0","at":1610163733,"name":"LINK/INR"},"sxpinr":{"base_unit":"sxp","quote_unit":"inr","low":"63.4","high":"85.1","last":"82.4","type":"SPOT","open":64.49,"volume":"441113.96","sell":"82.41","buy":"82.0","at":1610163733,"name":"SXP/INR"},"adainr":{"base_unit":"ada","quote_unit":"inr","low":"21.8","high":"24.69","last":"24.1","type":"SPOT","open":22.6221,"volume":"863503.3","sell":"24.1375","buy":"24.1","at":1610163733,"name":"ADA/INR"},"nanoinr":{"base_unit":"nano","quote_unit":"inr","low":"273.0","high":"273.0","last":"273.0","type":"SPOT","open":273.0,"volume":"0.0","sell":"390.0","buy":"273.0","at":1610163733,"name":"NANO/INR"},"atominr":{"base_unit":"atom","quote_unit":"inr","low":"450.0","high":"514.0","last":"510.0","type":"SPOT","open":484.9,"volume":"20597.51","sell":"511.92","buy":"501.0","at":1610163733,"name":"ATOM/INR"},"xlminr":{"base_unit":"xlm","quote_unit":"inr","low":"22.0016","high":"25.5","last":"23.1","type":"SPOT","open":23.16,"volume":"2438574.9","sell":"23.2929","buy":"23.1","at":1610163733,"name":"XLM/INR"},"fetinr":{"base_unit":"fet","quote_unit":"inr","low":"6.0","high":"6.0","last":"6.0","type":"SPOT","open":6.0,"volume":"0.0","sell":"6.0","buy":"3.7","at":1610163733,"name":"FET/INR"},"xeminr":{"base_unit":"xem","quote_unit":"inr","low":"17.6","high":"20.45","last":"18.15","type":"SPOT","open":18.2,"volume":"825672.0","sell":"18.15","buy":"18.1","at":1610163733,"name":"XEM/INR"},"zecinr":{"base_unit":"zec","quote_unit":"inr","low":"5025.0","high":"5450.0","last":"5350.95","type":"SPOT","open":5199.96,"volume":"177.109","sell":"5362.99","buy":"5300.0","at":1610163733,"name":"ZEC/INR"},"busdinr":{"base_unit":"busd","quote_unit":"inr","low":"77.0","high":"78.69","last":"78.44","type":"SPOT","open":77.7,"volume":"21071.43","sell":"78.43","buy":"78.2","at":1610163733,"name":"BUSD/INR"},"yfiiinr":{"base_unit":"yfii","quote_unit":"inr","low":"134000.0","high":"156000.0","last":"155456.5","type":"SPOT","open":135499.0,"volume":"673.848749","sell":"155441.04","buy":"155400.0","at":1610163733,"name":"YFII/INR"},"ltcinr":{"base_unit":"ltc","quote_unit":"inr","low":"12404.26","high":"14000.0","last":"13498.0","type":"SPOT","open":12501.0,"volume":"2703.994","sell":"13497.0","buy":"13465.0","at":1610163733,"name":"LTC/INR"},"dashinr":{"base_unit":"dash","quote_unit":"inr","low":"7449.0","high":"7780.0","last":"7550.0","type":"SPOT","open":7501.0,"volume":"273.57","sell":"7670.0","buy":"7550.0","at":1610163733,"name":"DASH/INR"},"xrpbtc":{"base_unit":"xrp","quote_unit":"btc","low":"0.00000755","high":"0.00000853","last":"0.00000807","type":"SPOT","open":7.99e-06,"volume":"59325.0","sell":"0.00000807","buy":"0.000008","at":1610163733,"name":"XRP/BTC"},"trxbtc":{"base_unit":"trx","quote_unit":"btc","low":"0.00000071","high":"0.00000081","last":"0.00000078","type":"SPOT","open":7.8e-07,"volume":"309470.0","sell":"0.00000078","buy":"0.00000074","at":1610163733,"name":"TRX/BTC"},"ethbtc":{"base_unit":"eth","quote_unit":"btc","low":"0.029196","high":"0.031122","last":"0.030337","type":"SPOT","open":0.030073,"volume":"88.553","sell":"0.030602","buy":"0.03043","at":1610163733,"name":"ETH/BTC"},"ncashbtc":{"base_unit":"ncash","quote_unit":"btc","low":"0.00000002","high":"0.00000004","last":"0.00000003","type":"SPOT","open":2.0e-08,"volume":"5053573.0","sell":"0.00000003","buy":"0.00000002","at":1610163733,"name":"NCASH/BTC"},"zilbtc":{"base_unit":"zil","quote_unit":"btc","low":"0.00000178","high":"0.00000196","last":"0.00000178","type":"SPOT","open":1.89e-06,"volume":"17978.0","sell":"0.00000183","buy":"0.00000181","at":1610163733,"name":"ZIL/BTC"},"batbtc":{"base_unit":"bat","quote_unit":"btc","low":"0.000006","high":"0.00000659","last":"0.00000605","type":"SPOT","open":6.59e-06,"volume":"2196.64","sell":"0.00000639","buy":"0.0000062","at":1610163733,"name":"BAT/BTC"},"ltcbtc":{"base_unit":"ltc","quote_unit":"btc","low":"0.004127","high":"0.004321","last":"0.004263","type":"SPOT","open":0.004161,"volume":"23.794","sell":"0.004295","buy":"0.004231","at":1610163733,"name":"LTC/BTC"},"qkcbtc":{"base_unit":"qkc","quote_unit":"btc","low":"0.00000013","high":"0.00000016","last":"0.00000014","type":"SPOT","open":1.6e-07,"volume":"21266.0","sell":"0.00000015","buy":"0.00000014","at":1610163733,"name":"QKC/BTC"},"npxsbtc":{"base_unit":"npxs","quote_unit":"btc","low":"0.00000001","high":"0.00000002","last":"0.00000001","type":"SPOT","open":1.0e-08,"volume":"165241575.0","sell":"0.00000002","buy":"0.00000001","at":1610163733,"name":"NPXS/BTC"},"dashbtc":{"base_unit":"dash","quote_unit":"btc","low":"0.002335","high":"0.002515","last":"0.002377","type":"SPOT","open":0.002474,"volume":"5.203","sell":"0.002438","buy":"0.002424","at":1610163733,"name":"DASH/BTC"},"funbtc":{"base_unit":"fun","quote_unit":"btc","low":"0.00000026","high":"0.00000033","last":"0.00000026","type":"SPOT","open":2.9e-07,"volume":"53176.0","sell":"0.0000003","buy":"0.00000029","at":1610163733,"name":"FUN/BTC"},"iostbtc":{"base_unit":"iost","quote_unit":"btc","low":"0.00000016","high":"0.0000003","last":"0.00000029","type":"SPOT","open":1.7e-07,"volume":"1496279.0","sell":"0.00000029","buy":"0.00000026","at":1610163733,"name":"IOST/BTC"},"nulsbtc":{"base_unit":"nuls","quote_unit":"btc","low":"0.00000603","high":"0.00000646","last":"0.00000646","type":"SPOT","open":6.55e-06,"volume":"3314.0","sell":"0.00000651","buy":"0.00000621","at":1610163733,"name":"NULS/BTC"},"omgbtc":{"base_unit":"omg","quote_unit":"btc","low":"0.000084","high":"0.000088","last":"0.000086","type":"SPOT","open":9.6e-05,"volume":"113.47","sell":"0.000088","buy":"0.000083","at":1610163733,"name":"OMG/BTC"},"poebtc":{"base_unit":"poe","quote_unit":"btc","low":"0.00000005","high":"0.00000005","last":"0.00000005","type":"SPOT","open":5.0e-08,"volume":"0.0","sell":"0.00000005","buy":"0.00000002","at":1610163733,"name":"POE/BTC"},"reqbtc":{"base_unit":"req","quote_unit":"btc","low":"0.00000064","high":"0.00000072","last":"0.00000067","type":"SPOT","open":7.0e-07,"volume":"269406.0","sell":"0.00000071","buy":"0.00000065","at":1610163733,"name":"REQ/BTC"},"sntbtc":{"base_unit":"snt","quote_unit":"btc","low":"0.00000139","high":"0.00000157","last":"0.00000149","type":"SPOT","open":1.73e-06,"volume":"4322.0","sell":"0.0000015","buy":"0.00000143","at":1610163733,"name":"SNT/BTC"},"thetabtc":{"base_unit":"theta","quote_unit":"btc","low":"0.00004652","high":"0.00005003","last":"0.00004784","type":"SPOT","open":4.869e-05,"volume":"190.0","sell":"0.00004909","buy":"0.0000485","at":1610163733,"name":"THETA/BTC"},"zrxbtc":{"base_unit":"zrx","quote_unit":"btc","low":"0.00001033","high":"0.00001141","last":"0.00001033","type":"SPOT","open":1.261e-05,"volume":"1219.07","sell":"0.00001146","buy":"0.0000108","at":1610163733,"name":"ZRX/BTC"},"eosbtc":{"base_unit":"eos","quote_unit":"btc","low":"0.0000747","high":"0.0000815","last":"0.0000769","type":"SPOT","open":7.97e-05,"volume":"161.82","sell":"0.0000789","buy":"0.0000765","at":1610163733,"name":"EOS/BTC"},"icxbtc":{"base_unit":"icx","quote_unit":"btc","low":"0.0000144","high":"0.0000155","last":"0.0000155","type":"SPOT","open":1.44e-05,"volume":"1532.76","sell":"0.000016","buy":"0.0000155","at":1610163733,"name":"ICX/BTC"},"hotbtc":{"base_unit":"hot","quote_unit":"btc","low":"0.00000002","high":"0.00000003","last":"0.00000003","type":"SPOT","open":3.0e-08,"volume":"477912.0","sell":"0.00000003","buy":"0.00000002","at":1610163733,"name":"HOT/BTC"},"polybtc":{"base_unit":"poly","quote_unit":"btc","low":"0.00000239","high":"0.0000027","last":"0.0000025","type":"SPOT","open":2.56e-06,"volume":"5042.0","sell":"0.00000252","buy":"0.0000024","at":1610163733,"name":"POLY/BTC"},"paxbtc":{"base_unit":"pax","quote_unit":"btc","low":"0.0","high":"0.0","last":"0.0","type":"SPOT","open":"0.0","volume":"0.0","sell":"0.0","buy":"0.00000001","at":1610163733,"name":"PAX/BTC"},"usdcbtc":{"base_unit":"usdc","quote_unit":"btc","low":"0.0","high":"0.0","last":"0.0","type":"SPOT","open":"0.0","volume":"0.0","sell":"0.0","buy":"0.0","at":1610163733,"name":"USDC/BTC"},"xlmbtc":{"base_unit":"xlm","quote_unit":"btc","low":"0.0","high":"0.0","last":"0.0","type":"SPOT","open":"0.0","volume":"0.0","sell":"0.0","buy":"0.00000001","at":1610163733,"name":"XLM/BTC"},"bttbtc":{"base_unit":"btt","quote_unit":"btc","low":"0.00000001","high":"0.00000002","last":"0.00000001","type":"SPOT","open":1.0e-08,"volume":"9169238.0","sell":"0.00000002","buy":"0.00000001","at":1610163733,"name":"BTT/BTC"},"fetbtc":{"base_unit":"fet","quote_unit":"btc","low":"0.00000165","high":"0.00000196","last":"0.00000185","type":"SPOT","open":1.81e-06,"volume":"3993.0","sell":"0.00000185","buy":"0.00000179","at":1610163733,"name":"FET/BTC"},"celrbtc":{"base_unit":"celr","quote_unit":"btc","low":"0.00000015","high":"0.00000018","last":"0.00000017","type":"SPOT","open":1.7e-07,"volume":"52161.0","sell":"0.00000018","buy":"0.00000015","at":1610163733,"name":"CELR/BTC"},"maticbtc":{"base_unit":"matic","quote_unit":"btc","low":"0.00000074","high":"0.00000084","last":"0.00000079","type":"SPOT","open":7.5e-07,"volume":"127736.2","sell":"0.0000008","buy":"0.00000076","at":1610163733,"name":"MATIC/BTC"},"adabtc":{"base_unit":"ada","quote_unit":"btc","low":"0.00000715","high":"0.00000836","last":"0.00000768","type":"SPOT","open":7.62e-06,"volume":"60322.8","sell":"0.00000771","buy":"0.00000757","at":1610163733,"name":"ADA/BTC"},"rvnbtc":{"base_unit":"rvn","quote_unit":"btc","low":"0.00000037","high":"0.00000042","last":"0.00000037","type":"SPOT","open":3.8e-07,"volume":"54160.0","sell":"0.00000042","buy":"0.00000039","at":1610163733,"name":"RVN/BTC"},"xmrbtc":{"base_unit":"xmr","quote_unit":"btc","low":"0.003489","high":"0.003775","last":"0.003491","type":"SPOT","open":0.003708,"volume":"4.666","sell":"0.003574","buy":"0.003532","at":1610163733,"name":"XMR/BTC"},"atombtc":{"base_unit":"atom","quote_unit":"btc","low":"0.0001454","high":"0.00016","last":"0.00016","type":"SPOT","open":0.0001576,"volume":"182.23","sell":"0.000165","buy":"0.0001621","at":1610163733,"name":"ATOM/BTC"},"bnbbtc":{"base_unit":"bnb","quote_unit":"btc","low":"0.0010233","high":"0.0011086","last":"0.0010618","type":"SPOT","open":0.0010903,"volume":"89.62","sell":"0.0010718","buy":"0.0010635","at":1610163733,"name":"BNB/BTC"},"wrxbtc":{"base_unit":"wrx","quote_unit":"btc","low":"0.00000197","high":"0.00000218","last":"0.00000208","type":"SPOT","open":2.15e-06,"volume":"33650.0","sell":"0.00000209","buy":"0.00000208","at":1610163733,"name":"WRX/BTC"},"fttbtc":{"base_unit":"ftt","quote_unit":"btc","low":"0.0002264","high":"0.0002369","last":"0.0002266","type":"SPOT","open":0.000234,"volume":"31.201","sell":"0.0002336","buy":"0.0002297","at":1610163733,"name":"FTT/BTC"},"stmxbtc":{"base_unit":"stmx","quote_unit":"btc","low":"0.00000006","high":"0.00000007","last":"0.00000007","type":"SPOT","open":7.0e-08,"volume":"90886.0","sell":"0.00000008","buy":"0.00000006","at":1610163733,"name":"STMX/BTC"},"glmbtc":{"base_unit":"glm","quote_unit":"btc","low":"0.0","high":"0.0","last":"0.0","type":"SPOT","open":"0.0","volume":"0.0","sell":"0.0","buy":"0.0","at":1610163733,"name":"GLM/BTC"},"btcusdt":{"base_unit":"btc","quote_unit":"usdt","low":"37528.0","high":"41974.0","last":"40131.0","type":"SPOT","open":38246.0,"volume":"39.3692","sell":"40250.0","buy":"40131.0","at":1610163733,"name":"BTC/USDT"},"trxusdt":{"base_unit":"trx","quote_unit":"usdt","low":"0.02926","high":"0.03129","last":"0.03091","type":"SPOT","open":0.02951,"volume":"4237552.0","sell":"0.031","buy":"0.03093","at":1610163733,"name":"TRX/USDT"},"xrpusdt":{"base_unit":"xrp","quote_unit":"usdt","low":"0.29752","high":"0.345","last":"0.3227","type":"SPOT","open":0.30172,"volume":"2041281.0","sell":"0.32245","buy":"0.32066","at":1610163733,"name":"XRP/USDT"},"eosusdt":{"base_unit":"eos","quote_unit":"usdt","low":"2.979","high":"3.2385","last":"3.0988","type":"SPOT","open":3.0207,"volume":"12896.76","sell":"3.1359","buy":"3.1129","at":1610163733,"name":"EOS/USDT"},"ethusdt":{"base_unit":"eth","quote_unit":"usdt","low":"1133.08","high":"1270.0","last":"1226.0","type":"SPOT","open":1149.3,"volume":"1131.671","sell":"1227.32","buy":"1223.5","at":1610163733,"name":"ETH/USDT"},"icxusdt":{"base_unit":"icx","quote_unit":"usdt","low":"0.5406","high":"0.633","last":"0.633","type":"SPOT","open":0.5404,"volume":"15092.31","sell":"0.6371","buy":"0.6335","at":1610163733,"name":"ICX/USDT"},"ltcusdt":{"base_unit":"ltc","quote_unit":"usdt","low":"156.5","high":"181.47","last":"171.85","type":"SPOT","open":158.35,"volume":"1499.601","sell":"171.63","buy":"170.21","at":1610163733,"name":"LTC/USDT"},"tusdusdt":{"base_unit":"tusd","quote_unit":"usdt","low":"0.9946","high":"1.0017","last":"0.9946","type":"SPOT","open":1.0017,"volume":"7.0","sell":"1.0034","buy":"0.9956","at":1610163733,"name":"TUSD/USDT"},"npxsusdt":{"base_unit":"npxs","quote_unit":"usdt","low":"0.000185","high":"0.000587","last":"0.00049","type":"SPOT","open":0.000187,"volume":"580746914.0","sell":"0.00049","buy":"0.000485","at":1610163733,"name":"NPXS/USDT"},"hotusdt":{"base_unit":"hot","quote_unit":"usdt","low":"0.00077","high":"0.0009","last":"0.0008715","type":"SPOT","open":0.00077,"volume":"4821238.0","sell":"0.0008822","buy":"0.0008715","at":1610163733,"name":"HOT/USDT"},"batusdt":{"base_unit":"bat","quote_unit":"usdt","low":"0.2418","high":"0.2662","last":"0.2529","type":"SPOT","open":0.2483,"volume":"182933.16","sell":"0.2541","buy":"0.2519","at":1610163733,"name":"BAT/USDT"},"dashusdt":{"base_unit":"dash","quote_unit":"usdt","low":"93.63","high":"100.43","last":"98.61","type":"SPOT","open":94.67,"volume":"301.41","sell":"98.91","buy":"98.36","at":1610163733,"name":"DASH/USDT"},"ncashusdt":{"base_unit":"ncash","quote_unit":"usdt","low":"0.000825","high":"0.0013","last":"0.001059","type":"SPOT","open":0.000825,"volume":"100569251.0","sell":"0.00106","buy":"0.001045","at":1610163733,"name":"NCASH/USDT"},"qkcusdt":{"base_unit":"qkc","quote_unit":"usdt","low":"0.00554","high":"0.00597","last":"0.00561","type":"SPOT","open":0.00565,"volume":"1602375.0","sell":"0.0059","buy":"0.00561","at":1610163733,"name":"QKC/USDT"},"zilusdt":{"base_unit":"zil","quote_unit":"usdt","low":"0.0709","high":"0.077","last":"0.07323","type":"SPOT","open":0.07156,"volume":"845683.0","sell":"0.07447","buy":"0.07376","at":1610163733,"name":"ZIL/USDT"},"zrxusdt":{"base_unit":"zrx","quote_unit":"usdt","low":"0.4231","high":"0.455","last":"0.448","type":"SPOT","open":0.4166,"volume":"10293.72","sell":"0.4481","buy":"0.4447","at":1610163733,"name":"ZRX/USDT"},"bchusdt":{"base_unit":"bch","quote_unit":"usdt","low":"413.0","high":"453.3","last":"433.2","type":"SPOT","open":420.29,"volume":"183.84","sell":"433.04","buy":"429.49","at":1610163733,"name":"BCH/USDT"},"bchsvusdt":{"base_unit":"bchsv","quote_unit":"usdt","low":"170.0","high":"183.68","last":"181.89","type":"SPOT","open":170.0,"volume":"17.276","sell":"181.95","buy":"173.79","at":1610163733,"name":"BCHSV/USDT"},"paxusdt":{"base_unit":"pax","quote_unit":"usdt","low":"0.9941","high":"1.0025","last":"0.9955","type":"SPOT","open":1.0025,"volume":"2743.41","sell":"0.9953","buy":"0.9952","at":1610163733,"name":"PAX/USDT"},"usdcusdt":{"base_unit":"usdc","quote_unit":"usdt","low":"0.996","high":"1.002","last":"1.002","type":"SPOT","open":1.002,"volume":"7210.21","sell":"1.0","buy":"0.996","at":1610163733,"name":"USDC/USDT"},"omgusdt":{"base_unit":"omg","quote_unit":"usdt","low":"3.2291","high":"3.5555","last":"3.4858","type":"SPOT","open":3.2789,"volume":"4208.8","sell":"3.4848","buy":"3.4584","at":1610163733,"name":"OMG/USDT"},"polyusdt":{"base_unit":"poly","quote_unit":"usdt","low":"0.096","high":"0.1077","last":"0.0967","type":"SPOT","open":0.0975,"volume":"51454.0","sell":"0.1","buy":"0.0975","at":1610163733,"name":"POLY/USDT"},"dentusdt":{"base_unit":"dent","quote_unit":"usdt","low":"0.000228","high":"0.000423","last":"0.000348","type":"SPOT","open":0.000231,"volume":"190434262.0","sell":"0.000348","buy":"0.000347","at":1610163733,"name":"DENT/USDT"},"iostusdt":{"base_unit":"iost","quote_unit":"usdt","low":"0.00613","high":"0.0115","last":"0.01095","type":"SPOT","open":0.0059,"volume":"14178870.0","sell":"0.01131","buy":"0.01098","at":1610163733,"name":"IOST/USDT"},"funusdt":{"base_unit":"fun","quote_unit":"usdt","low":"0.01081","high":"0.014","last":"0.011738","type":"SPOT","open":0.011,"volume":"3989784.0","sell":"0.011667","buy":"0.011405","at":1610163733,"name":"FUN/USDT"},"poeusdt":{"base_unit":"poe","quote_unit":"usdt","low":"0.000709","high":"0.000709","last":"0.000709","type":"SPOT","open":0.000709,"volume":"0.0","sell":"0.000828","buy":"0.000504","at":1610163733,"name":"POE/USDT"},"sntusdt":{"base_unit":"snt","quote_unit":"usdt","low":"0.05609","high":"0.06649","last":"0.05816","type":"SPOT","open":0.05574,"volume":"48966.0","sell":"0.05962","buy":"0.05816","at":1610163733,"name":"SNT/USDT"},"thetausdt":{"base_unit":"theta","quote_unit":"usdt","low":"1.85","high":"2.02692","last":"1.98164","type":"SPOT","open":1.87086,"volume":"12430.0","sell":"1.96697","buy":"1.955","at":1610163733,"name":"THETA/USDT"},"requsdt":{"base_unit":"req","quote_unit":"usdt","low":"0.02622","high":"0.02917","last":"0.02697","type":"SPOT","open":0.0276,"volume":"166810.0","sell":"0.02834","buy":"0.02715","at":1610163733,"name":"REQ/USDT"},"xlmusdt":{"base_unit":"xlm","quote_unit":"usdt","low":"0.27875","high":"0.3289","last":"0.29717","type":"SPOT","open":0.2871,"volume":"1552997.2","sell":"0.297","buy":"0.29491","at":1610163733,"name":"XLM/USDT"},"xtzusdt":{"base_unit":"xtz","quote_unit":"usdt","low":"2.3339","high":"2.5575","last":"2.5003","type":"SPOT","open":2.3,"volume":"2195.27","sell":"2.5238","buy":"2.5051","at":1610163733,"name":"XTZ/USDT"},"bttusdt":{"base_unit":"btt","quote_unit":"usdt","low":"0.0003204","high":"0.0005279","last":"0.0004371","type":"SPOT","open":0.0003389,"volume":"169246678.0","sell":"0.0004364","buy":"0.0004261","at":1610163733,"name":"BTT/USDT"},"fetusdt":{"base_unit":"fet","quote_unit":"usdt","low":"0.0642","high":"0.0809","last":"0.0747","type":"SPOT","open":0.0656,"volume":"553878.0","sell":"0.0749","buy":"0.073","at":1610163733,"name":"FET/USDT"},"tfuelusdt":{"base_unit":"tfuel","quote_unit":"usdt","low":"0.02531","high":"0.0282","last":"0.02637","type":"SPOT","open":0.02648,"volume":"855793.0","sell":"0.02637","buy":"0.02613","at":1610163733,"name":"TFUEL/USDT"},"celrusdt":{"base_unit":"celr","quote_unit":"usdt","low":"0.00628","high":"0.00713","last":"0.00713","type":"SPOT","open":0.00637,"volume":"1517182.0","sell":"0.00718","buy":"0.00709","at":1610163733,"name":"CELR/USDT"},"maticusdt":{"base_unit":"matic","quote_unit":"usdt","low":"0.02943","high":"0.035","last":"0.03157","type":"SPOT","open":0.02953,"volume":"3682072.3","sell":"0.03154","buy":"0.03125","at":1610163733,"name":"MATIC/USDT"},"adausdt":{"base_unit":"ada","quote_unit":"usdt","low":"0.27432","high":"0.32022","last":"0.30783","type":"SPOT","open":0.28523,"volume":"686290.6","sell":"0.30804","buy":"0.30642","at":1610163733,"name":"ADA/USDT"},"rvnusdt":{"base_unit":"rvn","quote_unit":"usdt","low":"0.01485","high":"0.01784","last":"0.01648","type":"SPOT","open":0.01505,"volume":"271181.0","sell":"0.01705","buy":"0.01662","at":1610163733,"name":"RVN/USDT"},"xmrusdt":{"base_unit":"xmr","quote_unit":"usdt","low":"140.56","high":"150.04","last":"141.26","type":"SPOT","open":138.74,"volume":"56.582","sell":"143.18","buy":"142.21","at":1610163733,"name":"XMR/USDT"},"atomusdt":{"base_unit":"atom","quote_unit":"usdt","low":"5.718","high":"6.6","last":"6.542","type":"SPOT","open":6.034,"volume":"12258.35","sell":"6.599","buy":"6.528","at":1610163733,"name":"ATOM/USDT"},"algousdt":{"base_unit":"algo","quote_unit":"usdt","low":"0.43","high":"0.486","last":"0.468","type":"SPOT","open":0.439,"volume":"35848.933","sell":"0.47","buy":"0.468","at":1610163733,"name":"ALGO/USDT"},"linkusdt":{"base_unit":"link","quote_unit":"usdt","low":"14.6247","high":"16.2347","last":"15.7884","type":"SPOT","open":15.0371,"volume":"5093.62","sell":"15.7174","buy":"15.712","at":1610163733,"name":"LINK/USDT"},"qtumusdt":{"base_unit":"qtum","quote_unit":"usdt","low":"2.75","high":"2.97","last":"2.97","type":"SPOT","open":2.75,"volume":"1232.192","sell":"2.952","buy":"2.925","at":1610163733,"name":"QTUM/USDT"},"etcusdt":{"base_unit":"etc","quote_unit":"usdt","low":"6.7","high":"7.1494","last":"6.9291","type":"SPOT","open":6.8966,"volume":"973.69","sell":"6.9223","buy":"6.8696","at":1610163733,"name":"ETC/USDT"},"iotausdt":{"base_unit":"iota","quote_unit":"usdt","low":"0.3476","high":"0.445","last":"0.4278","type":"SPOT","open":0.3624,"volume":"22682.68","sell":"0.4179","buy":"0.4137","at":1610163733,"name":"IOTA/USDT"},"zecusdt":{"base_unit":"zec","quote_unit":"usdt","low":"63.97","high":"69.74","last":"68.06","type":"SPOT","open":64.02,"volume":"245.289","sell":"68.16","buy":"67.68","at":1610163733,"name":"ZEC/USDT"},"wavesusdt":{"base_unit":"waves","quote_unit":"usdt","low":"5.4679","high":"5.923","last":"5.6707","type":"SPOT","open":5.5263,"volume":"1648.34","sell":"5.6737","buy":"5.62","at":1610163733,"name":"WAVES/USDT"},"ftmusdt":{"base_unit":"ftm","quote_unit":"usdt","low":"0.022","high":"0.0272","last":"0.02605","type":"SPOT","open":0.02194,"volume":"479106.4","sell":"0.02647","buy":"0.02618","at":1610163733,"name":"FTM/USDT"},"enjusdt":{"base_unit":"enj","quote_unit":"usdt","low":"0.19379","high":"0.27564","last":"0.19954","type":"SPOT","open":0.20501,"volume":"529375.7","sell":"0.20096","buy":"0.19954","at":1610163733,"name":"ENJ/USDT"},"lskusdt":{"base_unit":"lsk","quote_unit":"usdt","low":"1.2273","high":"1.3688","last":"1.3688","type":"SPOT","open":1.2273,"volume":"1233.92","sell":"1.3387","buy":"1.3218","at":1610163733,"name":"LSK/USDT"},"steemusdt":{"base_unit":"steem","quote_unit":"usdt","low":"0.1746","high":"0.192","last":"0.192","type":"SPOT","open":0.1746,"volume":"12753.68","sell":"0.1914","buy":"0.1885","at":1610163733,"name":"STEEM/USDT"},"xvgusdt":{"base_unit":"xvg","quote_unit":"usdt","low":"0.01323","high":"0.0168","last":"0.01385","type":"SPOT","open":0.01323,"volume":"1768398.0","sell":"0.01451","buy":"0.01385","at":1610163733,"name":"XVG/USDT"},"loomusdt":{"base_unit":"loom","quote_unit":"usdt","low":"0.04443","high":"0.05261","last":"0.04531","type":"SPOT","open":0.04685,"volume":"223956.0","sell":"0.04594","buy":"0.04516","at":1610163733,"name":"LOOM/USDT"},"manausdt":{"base_unit":"mana","quote_unit":"usdt","low":"0.11253","high":"0.15782","last":"0.114","type":"SPOT","open":0.13245,"volume":"280078.0","sell":"0.11376","buy":"0.113","at":1610163733,"name":"MANA/USDT"},"repusdt":{"base_unit":"rep","quote_unit":"usdt","low":"17.758","high":"19.275","last":"18.127","type":"SPOT","open":17.758,"volume":"47.758","sell":"18.38","buy":"18.198","at":1610163733,"name":"REP/USDT"},"blzusdt":{"base_unit":"blz","quote_unit":"usdt","low":"0.07292","high":"0.08285","last":"0.07965","type":"SPOT","open":0.07507,"volume":"296564.0","sell":"0.08042","buy":"0.07929","at":1610163733,"name":"BLZ/USDT"},"xzcusdt":{"base_unit":"xzc","quote_unit":"usdt","low":"3.197","high":"4.1","last":"3.65","type":"SPOT","open":3.198,"volume":"12974.69","sell":"3.65","buy":"3.588","at":1610163733,"name":"XZC/USDT"},"nanousdt":{"base_unit":"nano","quote_unit":"usdt","low":"3.4704","high":"4.75","last":"3.907","type":"SPOT","open":3.6534,"volume":"32985.52","sell":"4.057","buy":"3.9204","at":1610163733,"name":"NANO/USDT"},"scusdt":{"base_unit":"sc","quote_unit":"usdt","low":"0.00458","high":"0.00504","last":"0.00496","type":"SPOT","open":0.00478,"volume":"2328487.0","sell":"0.00497","buy":"0.00486","at":1610163733,"name":"SC/USDT"},"btgusdt":{"base_unit":"btg","quote_unit":"usdt","low":"10.2","high":"11.66","last":"10.68","type":"SPOT","open":11.24,"volume":"811.93","sell":"10.81","buy":"10.51","at":1610163733,"name":"BTG/USDT"},"xemusdt":{"base_unit":"xem","quote_unit":"usdt","low":"0.2225","high":"0.2678","last":"0.2324","type":"SPOT","open":0.2293,"volume":"615542.0","sell":"0.232","buy":"0.23","at":1610163733,"name":"XEM/USDT"},"btsusdt":{"base_unit":"bts","quote_unit":"usdt","low":"0.02577","high":"0.03","last":"0.02839","type":"SPOT","open":0.02678,"volume":"153244.0","sell":"0.0284","buy":"0.02837","at":1610163733,"name":"BTS/USDT"},"ardrusdt":{"base_unit":"ardr","quote_unit":"usdt","low":"0.07925","high":"0.08783","last":"0.08385","type":"SPOT","open":0.08,"volume":"8574.0","sell":"0.0816","buy":"0.08041","at":1610163733,"name":"ARDR/USDT"},"nasusdt":{"base_unit":"nas","quote_unit":"usdt","low":"0.2673","high":"0.3124","last":"0.3022","type":"SPOT","open":0.2673,"volume":"3257.92","sell":"0.3153","buy":"0.3026","at":1610163733,"name":"NAS/USDT"},"winusdt":{"base_unit":"win","quote_unit":"usdt","low":"0.000071","high":"0.0000855","last":"0.0000845","type":"SPOT","open":7.1e-05,"volume":"139356893.0","sell":"0.0000843","buy":"0.0000836","at":1610163733,"name":"WIN/USDT"},"bnbusdt":{"base_unit":"bnb","quote_unit":"usdt","low":"40.9653","high":"43.3666","last":"42.9956","type":"SPOT","open":41.4388,"volume":"779.52","sell":"42.9795","buy":"42.7441","at":1610163733,"name":"BNB/USDT"},"chzusdt":{"base_unit":"chz","quote_unit":"usdt","low":"0.018481","high":"0.020308","last":"0.019277","type":"SPOT","open":0.018707,"volume":"132623.0","sell":"0.019277","buy":"0.019247","at":1610163733,"name":"CHZ/USDT"},"wrxusdt":{"base_unit":"wrx","quote_unit":"usdt","low":"0.07893","high":"0.084","last":"0.08227","type":"SPOT","open":0.07955,"volume":"1277039.0","sell":"0.08273","buy":"0.08227","at":1610163733,"name":"WRX/USDT"},"kavausdt":{"base_unit":"kava","quote_unit":"usdt","low":"1.503","high":"1.75","last":"1.6629","type":"SPOT","open":1.5374,"volume":"10373.49","sell":"1.6846","buy":"1.6751","at":1610163733,"name":"KAVA/USDT"},"ankrusdt":{"base_unit":"ankr","quote_unit":"usdt","low":"0.008475","high":"0.009741","last":"0.009741","type":"SPOT","open":0.008658,"volume":"5014649.0","sell":"0.009799","buy":"0.009735","at":1610163733,"name":"ANKR/USDT"},"busdusdt":{"base_unit":"busd","quote_unit":"usdt","low":"0.9962","high":"1.005","last":"0.9969","type":"SPOT","open":0.9966,"volume":"18168.51","sell":"1.0","buy":"0.9969","at":1610163733,"name":"BUSD/USDT"},"oneusdt":{"base_unit":"one","quote_unit":"usdt","low":"0.00583","high":"0.00774","last":"0.00733","type":"SPOT","open":0.00591,"volume":"2591043.0","sell":"0.00739","buy":"0.00734","at":1610163733,"name":"ONE/USDT"},"ognusdt":{"base_unit":"ogn","quote_unit":"usdt","low":"0.0","high":"0.0","last":"0.0","type":"SPOT","open":"0.0","volume":"0.0","sell":"0.0","buy":"0.0","at":1610163733,"name":"OGN/USDT"},"hiveusdt":{"base_unit":"hive","quote_unit":"usdt","low":"0.1143","high":"0.1313","last":"0.1279","type":"SPOT","open":0.1127,"volume":"49502.71","sell":"0.128","buy":"0.123","at":1610163733,"name":"HIVE/USDT"},"fttusdt":{"base_unit":"ftt","quote_unit":"usdt","low":"8.581","high":"9.62","last":"9.197","type":"SPOT","open":8.893,"volume":"259.271","sell":"9.326","buy":"9.263","at":1610163733,"name":"FTT/USDT"},"bandusdt":{"base_unit":"band","quote_unit":"usdt","low":"8.1378","high":"11.1963","last":"11.0608","type":"SPOT","open":7.9681,"volume":"12310.72","sell":"11.0989","buy":"11.0185","at":1610163733,"name":"BAND/USDT"},"jstusdt":{"base_unit":"jst","quote_unit":"usdt","low":"0.025","high":"0.02925","last":"0.02591","type":"SPOT","open":0.02536,"volume":"251278.0","sell":"0.02655","buy":"0.02599","at":1610163733,"name":"JST/USDT"},"ctsiusdt":{"base_unit":"ctsi","quote_unit":"usdt","low":"0.04426","high":"0.05","last":"0.04928","type":"SPOT","open":0.04426,"volume":"217513.6","sell":"0.04938","buy":"0.04903","at":1610163733,"name":"CTSI/USDT"},"chrusdt":{"base_unit":"chr","quote_unit":"usdt","low":"0.02314","high":"0.0262","last":"0.0262","type":"SPOT","open":0.02314,"volume":"600346.0","sell":"0.02622","buy":"0.02592","at":1610163733,"name":"CHR/USDT"},"tomousdt":{"base_unit":"tomo","quote_unit":"usdt","low":"0.8495","high":"1.2","last":"1.1674","type":"SPOT","open":0.8495,"volume":"34079.17","sell":"1.1757","buy":"1.1649","at":1610163733,"name":"TOMO/USDT"},"stxusdt":{"base_unit":"stx","quote_unit":"usdt","low":"0.0","high":"0.0","last":"0.0","type":"SPOT","open":"0.0","volume":"0.0","sell":"0.0","buy":"0.0","at":1610163733,"name":"STX/USDT"},"stmxusdt":{"base_unit":"stmx","quote_unit":"usdt","low":"0.0024","high":"0.003173","last":"0.002796","type":"SPOT","open":0.002437,"volume":"1648447.0","sell":"0.002827","buy":"0.002816","at":1610163733,"name":"STMX/USDT"},"gxsusdt":{"base_unit":"gxs","quote_unit":"usdt","low":"0.3072","high":"0.3331","last":"0.3315","type":"SPOT","open":0.3072,"volume":"2551.09","sell":"0.339","buy":"0.3329","at":1610163733,"name":"GXS/USDT"},"mdtusdt":{"base_unit":"mdt","quote_unit":"usdt","low":"0.0","high":"0.0","last":"0.0","type":"SPOT","open":"0.0","volume":"0.0","sell":"0.0","buy":"0.0","at":1610163733,"name":"MDT/USDT"},"ltousdt":{"base_unit":"lto","quote_unit":"usdt","low":"0.0","high":"0.0","last":"0.0","type":"SPOT","open":"0.0","volume":"0.0","sell":"0.0","buy":"0.0","at":1610163733,"name":"LTO/USDT"},"lrcusdt":{"base_unit":"lrc","quote_unit":"usdt","low":"0.32554","high":"0.42576","last":"0.42576","type":"SPOT","open":0.34064,"volume":"180876.0","sell":"0.41795","buy":"0.41356","at":1610163733,"name":"LRC/USDT"},"dogeusdt":{"base_unit":"doge","quote_unit":"usdt","low":"0.0091748","high":"0.0102","last":"0.0100875","type":"SPOT","open":0.0093452,"volume":"5095126.0","sell":"0.010179","buy":"0.010067","at":1610163733,"name":"DOGE/USDT"},"neousdt":{"base_unit":"neo","quote_unit":"usdt","low":"19.0","high":"21.253","last":"20.234","type":"SPOT","open":19.383,"volume":"563.027","sell":"20.263","buy":"20.105","at":1610163733,"name":"NEO/USDT"},"hbarusdt":{"base_unit":"hbar","quote_unit":"usdt","low":"0.0","high":"0.0","last":"0.0","type":"SPOT","open":"0.0","volume":"0.0","sell":"0.0","buy":"0.0","at":1610163733,"name":"HBAR/USDT"},"storjusdt":{"base_unit":"storj","quote_unit":"usdt","low":"0.3244","high":"0.414","last":"0.3698","type":"SPOT","open":0.3244,"volume":"48106.0","sell":"0.3735","buy":"0.37","at":1610163733,"name":"STORJ/USDT"},"compusdt":{"base_unit":"comp","quote_unit":"usdt","low":"157.0","high":"177.33","last":"166.05","type":"SPOT","open":157.73,"volume":"98.095","sell":"169.91","buy":"168.15","at":1610163733,"name":"COMP/USDT"},"cotiusdt":{"base_unit":"coti","quote_unit":"usdt","low":"0.05288","high":"0.062","last":"0.0585","type":"SPOT","open":0.05288,"volume":"213090.3","sell":"0.05918","buy":"0.0586","at":1610163733,"name":"COTI/USDT"},"dgbusdt":{"base_unit":"dgb","quote_unit":"usdt","low":"0.02882","high":"0.03236","last":"0.02993","type":"SPOT","open":0.03142,"volume":"138554.0","sell":"0.03025","buy":"0.02992","at":1610163733,"name":"DGB/USDT"},"grsusdt":{"base_unit":"grs","quote_unit":"usdt","low":"0.37","high":"0.4147","last":"0.3729","type":"SPOT","open":0.3765,"volume":"19543.0","sell":"0.38","buy":"0.3771","at":1610163733,"name":"GRS/USDT"},"snxusdt":{"base_unit":"snx","quote_unit":"usdt","low":"10.811","high":"12.887","last":"11.485","type":"SPOT","open":10.9,"volume":"1785.079","sell":"11.56","buy":"11.485","at":1610163733,"name":"SNX/USDT"},"renusdt":{"base_unit":"ren","quote_unit":"usdt","low":"0.3513","high":"0.4112","last":"0.38427","type":"SPOT","open":0.35108,"volume":"8364.0","sell":"0.38826","buy":"0.38417","at":1610163733,"name":"REN/USDT"},"sxpusdt":{"base_unit":"sxp","quote_unit":"usdt","low":"0.808","high":"1.099","last":"1.058","type":"SPOT","open":0.821,"volume":"304404.18","sell":"1.061","buy":"1.057","at":1610163733,"name":"SXP/USDT"},"mkrusdt":{"base_unit":"mkr","quote_unit":"usdt","low":"1012.7","high":"1113.51","last":"1080.0","type":"SPOT","open":1050.0,"volume":"4.26291","sell":"1093.06","buy":"1081.96","at":1610163733,"name":"MKR/USDT"},"daiusdt":{"base_unit":"dai","quote_unit":"usdt","low":"0.0","high":"0.0","last":"0.0","type":"SPOT","open":"0.0","volume":"0.0","sell":"0.0","buy":"0.0","at":1610163733,"name":"DAI/USDT"},"avausdt":{"base_unit":"ava","quote_unit":"usdt","low":"0.8813","high":"1.0494","last":"1.0","type":"SPOT","open":0.9101,"volume":"11431.08","sell":"1.0391","buy":"1.0103","at":1610163733,"name":"AVA/USDT"},"balusdt":{"base_unit":"bal","quote_unit":"usdt","low":"0.0","high":"0.0","last":"0.0","type":"SPOT","open":"0.0","volume":"0.0","sell":"0.0","buy":"0.0","at":1610163733,"name":"BAL/USDT"},"srmusdt":{"base_unit":"srm","quote_unit":"usdt","low":"1.3051","high":"1.866","last":"1.624","type":"SPOT","open":1.313,"volume":"108102.71","sell":"1.6238","buy":"1.51","at":1610163733,"name":"SRM/USDT"},"egldusdt":{"base_unit":"egld","quote_unit":"usdt","low":"35.197","high":"40.877","last":"36.887","type":"SPOT","open":35.594,"volume":"436.332","sell":"37.099","buy":"36.716","at":1610163733,"name":"EGLD/USDT"},"cosusdt":{"base_unit":"cos","quote_unit":"usdt","low":"0.0075","high":"0.00806","last":"0.0079","type":"SPOT","open":0.0075,"volume":"102727.7","sell":"0.00793","buy":"0.0079","at":1610163733,"name":"COS/USDT"},"nbsusdt":{"base_unit":"nbs","quote_unit":"usdt","low":"0.013685","high":"0.014859","last":"0.01397","type":"SPOT","open":0.01396,"volume":"113962.0","sell":"0.01405","buy":"0.013989","at":1610163733,"name":"NBS/USDT"},"aionusdt":{"base_unit":"aion","quote_unit":"usdt","low":"0.0749","high":"0.0821","last":"0.081","type":"SPOT","open":0.0756,"volume":"39202.45","sell":"0.0812","buy":"0.0798","at":1610163733,"name":"AION/USDT"},"dotusdt":{"base_unit":"dot","quote_unit":"usdt","low":"9.0","high":"9.7873","last":"9.1912","type":"SPOT","open":9.3295,"volume":"9214.15","sell":"9.1912","buy":"9.1693","at":1610163733,"name":"DOT/USDT"},"yfiusdt":{"base_unit":"yfi","quote_unit":"usdt","low":"28845.01","high":"38100.0","last":"36154.76","type":"SPOT","open":29281.45,"volume":"22.849775","sell":"36600.0","buy":"36323.25","at":1610163733,"name":"YFI/USDT"},"iotxusdt":{"base_unit":"iotx","quote_unit":"usdt","low":"0.006892","high":"0.007706","last":"0.007706","type":"SPOT","open":0.006853,"volume":"33809.0","sell":"0.007706","buy":"0.007556","at":1610163733,"name":"IOTX/USDT"},"sandusdt":{"base_unit":"sand","quote_unit":"usdt","low":"0.042","high":"0.047005","last":"0.043147","type":"SPOT","open":0.041207,"volume":"149191.0","sell":"0.044","buy":"0.043457","at":1610163733,"name":"SAND/USDT"},"uniusdt":{"base_unit":"uni","quote_unit":"usdt","low":"5.6594","high":"6.3527","last":"6.0598","type":"SPOT","open":5.8532,"volume":"14078.34","sell":"6.1056","buy":"6.0492","at":1610163733,"name":"UNI/USDT"},"datausdt":{"base_unit":"data","quote_unit":"usdt","low":"0.04542","high":"0.07043","last":"0.06213","type":"SPOT","open":0.04409,"volume":"472798.0","sell":"0.06372","buy":"0.06262","at":1610163733,"name":"DATA/USDT"},"paxgusdt":{"base_unit":"paxg","quote_unit":"usdt","low":"0.0","high":"0.0","last":"0.0","type":"SPOT","open":"0.0","volume":"0.0","sell":"0.0","buy":"0.0","at":1610163733,"name":"PAXG/USDT"},"creamusdt":{"base_unit":"cream","quote_unit":"usdt","low":"75.0","high":"93.0","last":"79.322","type":"SPOT","open":73.85,"volume":"593.457","sell":"80.0","buy":"75.5","at":1610163733,"name":"CREAM/USDT"},"swrvusdt":{"base_unit":"swrv","quote_unit":"usdt","low":"0.0","high":"0.0","last":"0.0","type":"SPOT","open":"0.0","volume":"0.0","sell":"0.0","buy":"0.0","at":1610163733,"name":"SWRV/USDT"},"umausdt":{"base_unit":"uma","quote_unit":"usdt","low":"9.09","high":"10.0","last":"9.401","type":"SPOT","open":9.09,"volume":"251.664","sell":"9.535","buy":"9.378","at":1610163733,"name":"UMA/USDT"},"diausdt":{"base_unit":"dia","quote_unit":"usdt","low":"0.0","high":"0.0","last":"0.0","type":"SPOT","open":"0.0","volume":"0.0","sell":"0.0","buy":"0.0","at":1610163733,"name":"DIA/USDT"},"ksmusdt":{"base_unit":"ksm","quote_unit":"usdt","low":"0.0","high":"0.0","last":"0.0","type":"SPOT","open":"0.0","volume":"0.0","sell":"0.0","buy":"0.0","at":1610163733,"name":"KSM/USDT"},"yfiiusdt":{"base_unit":"yfii","quote_unit":"usdt","low":"1679.3","high":"2028.88","last":"2001.82","type":"SPOT","open":1738.73,"volume":"288.734298","sell":"2009.0","buy":"1998.65","at":1610163733,"name":"YFII/USDT"},"bzrxusdt":{"base_unit":"bzrx","quote_unit":"usdt","low":"0.0","high":"0.0","last":"0.0","type":"SPOT","open":"0.0","volume":"0.0","sell":"0.0","buy":"0.0","at":1610163733,"name":"BZRX/USDT"},"trbusdt":{"base_unit":"trb","quote_unit":"usdt","low":"0.0","high":"0.0","last":"0.0","type":"SPOT","open":"0.0","volume":"0.0","sell":"0.0","buy":"0.0","at":1610163733,"name":"TRB/USDT"},"adxusdt":{"base_unit":"adx","quote_unit":"usdt","low":"0.3684","high":"0.3909","last":"0.3724","type":"SPOT","open":0.38,"volume":"1209.0","sell":"0.3709","buy":"0.365","at":1610163733,"name":"ADX/USDT"},"aaveusdt":{"base_unit":"aave","quote_unit":"usdt","low":"104.888","high":"117.447","last":"112.514","type":"SPOT","open":106.223,"volume":"102.132","sell":"112.559","buy":"111.353","at":1610163733,"name":"AAVE/USDT"},"filusdt":{"base_unit":"fil","quote_unit":"usdt","low":"21.1839","high":"22.1734","last":"21.7524","type":"SPOT","open":21.2977,"volume":"197.99","sell":"21.8424","buy":"21.4438","at":1610163733,"name":"FIL/USDT"},"crvusdt":{"base_unit":"crv","quote_unit":"usdt","low":"0.654","high":"0.741","last":"0.741","type":"SPOT","open":0.662,"volume":"20417.348","sell":"0.74","buy":"0.736","at":1610163733,"name":"CRV/USDT"},"nearusdt":{"base_unit":"near","quote_unit":"usdt","low":"1.4684","high":"1.9542","last":"1.6735","type":"SPOT","open":1.4715,"volume":"3398.094","sell":"1.7463","buy":"1.7114","at":1610163733,"name":"NEAR/USDT"},"hntusdt":{"base_unit":"hnt","quote_unit":"usdt","low":"1.3","high":"1.45","last":"1.437","type":"SPOT","open":1.33,"volume":"594.49","sell":"1.449","buy":"1.437","at":1610163733,"name":"HNT/USDT"},"avaxusdt":{"base_unit":"avax","quote_unit":"usdt","low":"4.82","high":"6.6798","last":"6.28","type":"SPOT","open":4.2,"volume":"1242.66","sell":"6.3785","buy":"6.3008","at":1610163733,"name":"AVAX/USDT"},"oxtusdt":{"base_unit":"oxt","quote_unit":"usdt","low":"0.265","high":"0.2804","last":"0.2778","type":"SPOT","open":0.265,"volume":"8318.85","sell":"0.2808","buy":"0.276","at":1610163733,"name":"OXT/USDT"},"dockusdt":{"base_unit":"dock","quote_unit":"usdt","low":"0.018772","high":"0.019792","last":"0.019093","type":"SPOT","open":0.019593,"volume":"100245.0","sell":"0.019137","buy":"0.018565","at":1610163733,"name":"DOCK/USDT"},"duskusdt":{"base_unit":"dusk","quote_unit":"usdt","low":"0.055","high":"0.0615","last":"0.0579","type":"SPOT","open":0.056,"volume":"77421.76","sell":"0.0594","buy":"0.0584","at":1610163733,"name":"DUSK/USDT"},"wtcusdt":{"base_unit":"wtc","quote_unit":"usdt","low":"0.3309","high":"0.3558","last":"0.3372","type":"SPOT","open":0.3558,"volume":"1489.89","sell":"0.3486","buy":"0.3434","at":1610163733,"name":"WTC/USDT"},"perlusdt":{"base_unit":"perl","quote_unit":"usdt","low":"0.0","high":"0.0","last":"0.0","type":"SPOT","open":"0.0","volume":"0.0","sell":"0.0","buy":"0.0","at":1610163733,"name":"PERL/USDT"},"straxusdt":{"base_unit":"strax","quote_unit":"usdt","low":"0.469","high":"0.4973","last":"0.4939","type":"SPOT","open":0.4801,"volume":"25240.54","sell":"0.4969","buy":"0.4939","at":1610163733,"name":"STRAX/USDT"},"injusdt":{"base_unit":"inj","quote_unit":"usdt","low":"4.4948","high":"4.948","last":"4.6245","type":"SPOT","open":4.4948,"volume":"6901.92","sell":"4.6255","buy":"4.5779","at":1610163733,"name":"INJ/USDT"},"vetusdt":{"base_unit":"vet","quote_unit":"usdt","low":"0.0257","high":"0.034412","last":"0.02825","type":"SPOT","open":0.03,"volume":"3188384.0","sell":"0.028169","buy":"0.028081","at":1610163733,"name":"VET/USDT"},"mtlusdt":{"base_unit":"mtl","quote_unit":"usdt","low":"0.3602","high":"0.4179","last":"0.38","type":"SPOT","open":0.3602,"volume":"469.79","sell":"0.4129","buy":"0.3676","at":1610163733,"name":"MTL/USDT"},"frontusdt":{"base_unit":"front","quote_unit":"usdt","low":"0.32","high":"0.398","last":"0.373","type":"SPOT","open":0.3334,"volume":"51873.01","sell":"0.377","buy":"0.3601","at":1610163733,"name":"FRONT/USDT"},"glmusdt":{"base_unit":"glm","quote_unit":"usdt","low":"0.1178","high":"0.1307","last":"0.1214","type":"SPOT","open":0.1277,"volume":"8538.0","sell":"0.1228","buy":"0.1191","at":1610163733,"name":"GLM/USDT"},"sushiusdt":{"base_unit":"sushi","quote_unit":"usdt","low":"3.569","high":"4.476","last":"4.405","type":"SPOT","open":3.569,"volume":"5525.708","sell":"4.433","buy":"4.414","at":1610163733,"name":"SUSHI/USDT"},"ethwrx":{"base_unit":"eth","quote_unit":"wrx","low":"14220.0","high":"15282.0","last":"14752.0","type":"SPOT","open":14225.0,"volume":"30.286","sell":"14848.0","buy":"14694.0","at":1610163733,"name":"ETH/WRX"},"xrpwrx":{"base_unit":"xrp","quote_unit":"wrx","low":"3.75","high":"4.11","last":"3.89","type":"SPOT","open":3.76,"volume":"50424.0","sell":"3.9","buy":"3.85","at":1610163733,"name":"XRP/WRX"},"yfiwrx":{"base_unit":"yfi","quote_unit":"wrx","low":"368886.0","high":"460000.0","last":"443854.0","type":"SPOT","open":362782.0,"volume":"0.450878","sell":"444079.0","buy":"437692.0","at":1610163733,"name":"YFI/WRX"},"bnbwrx":{"base_unit":"bnb","quote_unit":"wrx","low":"512.0","high":"527.0","last":"522.0","type":"SPOT","open":527.0,"volume":"25.32","sell":"520.0","buy":"513.0","at":1610163733,"name":"BNB/WRX"},"trxwrx":{"base_unit":"trx","quote_unit":"wrx","low":"0.3631","high":"0.3769","last":"0.3721","type":"SPOT","open":0.3737,"volume":"37492.0","sell":"0.3719","buy":"0.3717","at":1610163733,"name":"TRX/WRX"},"eoswrx":{"base_unit":"eos","quote_unit":"wrx","low":"37.51","high":"450.0","last":"37.85","type":"SPOT","open":"37.85","volume":"1804.16","sell":"38.08","buy":"37.62","at":1610163733,"name":"EOS/WRX"}}