{"btcinr":{"base_unit":"btc","quote_unit":"inr","low":"2850000.0","high":"3245030.0","last":"3109860.0","type":"SPOT","open":3023855.0,"volume":"377.6495","sell":"3113960.0","buy":"3113800.0","at":1610177490,"name":"BTC/INR"},"xrpinr":{"base_unit":"xrp","quote_unit":"inr","low":"22.6","high":"27.7","last":"24.9","type":"SPOT","open":24.59,"volume":"5090694.0","sell":"24.8999","buy":"24.8501","at":1610177490,"name":"XRP/INR"},"ethinr":{"base_unit":"eth","quote_unit":"inr","low":"91000.0","high":"97700.2","last":"94300.0","type":"SPOT","open":92529.7,"volume":"2740.703","sell":"94305.0","buy":"94286.6","at":1610177490,"name":"ETH/INR"},"trxinr":{"base_unit":"trx","quote_unit":"inr","low":"2.32","high":"2.4489","last":"2.41","type":"SPOT","open":2.3857,"volume":"14808116.0","sell":"2.41","buy":"2.4096","at":1610177490,"name":"TRX/INR"},"eosinr":{"base_unit":"eos","quote_unit":"inr","low":"235.0","high":"250.0","last":"240.0","type":"SPOT","open":245.5,"volume":"12504.61","sell":"244.0","buy":"239.97","at":1610177490,"name":"EOS/INR"},"zilinr":{"base_unit":"zil","quote_unit":"inr","low":"5.64","high":"5.95","last":"5.76","type":"SPOT","open":5.81,"volume":"3093.0","sell":"5.94","buy":"5.63","at":1610177490,"name":"ZIL/INR"},"batinr":{"base_unit":"bat","quote_unit":"inr","low":"19.001","high":"20.998","last":"20.101","type":"SPOT","open":20.28,"volume":"213031.95","sell":"20.16","buy":"19.661","at":1610177490,"name":"BAT/INR"},"usdtinr":{"base_unit":"usdt","quote_unit":"inr","low":"76.8","high":"79.0","last":"78.5","type":"SPOT","open":78.04,"volume":"5684997.21","sell":"78.6","buy":"78.46","at":1610177490,"name":"USDT/INR"},"wrxinr":{"base_unit":"wrx","quote_unit":"inr","low":"6.21","high":"6.99","last":"6.96","type":"SPOT","open":6.36,"volume":"3222993.0","sell":"6.96","buy":"6.95","at":1610177490,"name":"WRX/INR"},"maticinr":{"base_unit":"matic","quote_unit":"inr","low":"2.402","high":"2.65","last":"2.482","type":"SPOT","open":2.46,"volume":"6776892.0","sell":"2.478","buy":"2.46","at":1610177490,"name":"MATIC/INR"},"bchinr":{"base_unit":"bch","quote_unit":"inr","low":"33350.0","high":"35499.0","last":"33450.0","type":"SPOT","open":33869.0,"volume":"234.359","sell":"33450.0","buy":"33356.0","at":1610177490,"name":"BCH/INR"},"bnbinr":{"base_unit":"bnb","quote_unit":"inr","low":"3240.0","high":"3383.0","last":"3348.59","type":"SPOT","open":3257.04,"volume":"868.1241","sell":"3349.0","buy":"3301.0","at":1610177490,"name":"BNB/INR"},"bttinr":{"base_unit":"btt","quote_unit":"inr","low":"0.02525","high":"0.04199","last":"0.03249","type":"SPOT","open":0.02568,"volume":"548199118.0","sell":"0.03249","buy":"0.03201","at":1610177490,"name":"BTT/INR"},"chzinr":{"base_unit":"chz","quote_unit":"inr","low":"1.999","high":"1.999","last":"1.999","type":"SPOT","open":1.999,"volume":"0.0","sell":"1.991","buy":"1.301","at":1610177490,"name":"CHZ/INR"},"oneinr":{"base_unit":"one","quote_unit":"inr","low":"0.47","high":"0.6698","last":"0.66","type":"SPOT","open":0.48,"volume":"131237.0","sell":"0.68","buy":"0.43","at":1610177490,"name":"ONE/INR"},"yfiinr":{"base_unit":"yfi","quote_unit":"inr","low":"2430656.0","high":"2980739.0","last":"2885491.0","type":"SPOT","open":2410999.0,"volume":"33.200439","sell":"2886166.0","buy":"2885491.0","at":1610177490,"name":"YFI/INR"},"uniinr":{"base_unit":"uni","quote_unit":"inr","low":"445.0","high":"490.0","last":"465.0","type":"SPOT","open":469.9,"volume":"19116.35","sell":"469.95","buy":"465.0","at":1610177490,"name":"UNI/INR"},"linkinr":{"base_unit":"link","quote_unit":"inr","low":"1153.18","high":"1254.99","last":"1219.99","type":"SPOT","open":1207.0,"volume":"3787.06","sell":"1219.85","buy":"1197.03","at":1610177490,"name":"LINK/INR"},"sxpinr":{"base_unit":"sxp","quote_unit":"inr","low":"65.15","high":"85.1","last":"80.9","type":"SPOT","open":66.4,"volume":"468715.62","sell":"81.0","buy":"80.9","at":1610177490,"name":"SXP/INR"},"adainr":{"base_unit":"ada","quote_unit":"inr","low":"22.51","high":"24.69","last":"23.8","type":"SPOT","open":23.9058,"volume":"695147.1","sell":"23.9","buy":"23.8","at":1610177490,"name":"ADA/INR"},"nanoinr":{"base_unit":"nano","quote_unit":"inr","low":"273.0","high":"273.0","last":"273.0","type":"SPOT","open":273.0,"volume":"0.0","sell":"390.0","buy":"65.0","at":1610177490,"name":"NANO/INR"},"atominr":{"base_unit":"atom","quote_unit":"inr","low":"450.0","high":"514.0","last":"497.7","type":"SPOT","open":479.0,"volume":"21437.29","sell":"497.7","buy":"491.02","at":1610177490,"name":"ATOM/INR"},"xlminr":{"base_unit":"xlm","quote_unit":"inr","low":"22.1","high":"25.5","last":"22.6994","type":"SPOT","open":24.0024,"volume":"2282657.0","sell":"22.6994","buy":"22.68","at":1610177490,"name":"XLM/INR"},"fetinr":{"base_unit":"fet","quote_unit":"inr","low":"6.0","high":"6.0","last":"6.0","type":"SPOT","open":6.0,"volume":"101.0","sell":"7.0","buy":"3.7","at":1610177490,"name":"FET/INR"},"xeminr":{"base_unit":"xem","quote_unit":"inr","low":"17.6","high":"20.45","last":"17.96","type":"SPOT","open":18.423,"volume":"985073.0","sell":"17.961","buy":"17.801","at":1610177490,"name":"XEM/INR"},"zecinr":{"base_unit":"zec","quote_unit":"inr","low":"5149.99","high":"5450.0","last":"5308.95","type":"SPOT","open":5189.0,"volume":"150.388","sell":"5308.95","buy":"5217.03","at":1610177490,"name":"ZEC/INR"},"busdinr":{"base_unit":"busd","quote_unit":"inr","low":"77.0","high":"78.69","last":"78.4","type":"SPOT","open":78.69,"volume":"26259.71","sell":"78.3","buy":"77.53","at":1610177490,"name":"BUSD/INR"},"yfiiinr":{"base_unit":"yfii","quote_unit":"inr","low":"138950.0","high":"158500.0","last":"155000.0","type":"SPOT","open":140000.0,"volume":"668.745817","sell":"155484.49","buy":"155000.0","at":1610177490,"name":"YFII/INR"},"ltcinr":{"base_unit":"ltc","quote_unit":"inr","low":"12637.7","high":"14000.0","last":"13218.68","type":"SPOT","open":12648.0,"volume":"2640.862","sell":"13218.68","buy":"13097.28","at":1610177490,"name":"LTC/INR"},"dashinr":{"base_unit":"dash","quote_unit":"inr","low":"7449.0","high":"7780.0","last":"7698.0","type":"SPOT","open":7450.0,"volume":"273.034","sell":"7698.0","buy":"7611.0","at":1610177490,"name":"DASH/INR"},"xrpbtc":{"base_unit":"xrp","quote_unit":"btc","low":"0.00000755","high":"0.00000853","last":"0.00000798","type":"SPOT","open":8.03e-06,"volume":"50309.0","sell":"0.00000798","buy":"0.0000079","at":1610177490,"name":"XRP/BTC"},"trxbtc":{"base_unit":"trx","quote_unit":"btc","low":"0.00000071","high":"0.00000081","last":"0.00000077","type":"SPOT","open":7.9e-07,"volume":"359015.0","sell":"0.00000079","buy":"0.00000077","at":1610177490,"name":"TRX/BTC"},"ethbtc":{"base_unit":"eth","quote_unit":"btc","low":"0.029196","high":"0.031122","last":"0.030345","type":"SPOT","open":0.030623,"volume":"86.029","sell":"0.0303","buy":"0.030174","at":1610177490,"name":"ETH/BTC"},"ncashbtc":{"base_unit":"ncash","quote_unit":"btc","low":"0.00000002","high":"0.00000004","last":"0.00000002","type":"SPOT","open":2.0e-08,"volume":"5604723.0","sell":"0.00000003","buy":"0.00000002","at":1610177490,"name":"NCASH/BTC"},"zilbtc":{"base_unit":"zil","quote_unit":"btc","low":"0.00000178","high":"0.00000196","last":"0.00000183","type":"SPOT","open":1.92e-06,"volume":"11719.0","sell":"0.00000185","buy":"0.00000181","at":1610177490,"name":"ZIL/BTC"},"batbtc":{"base_unit":"bat","quote_unit":"btc","low":"0.000006","high":"0.00000649","last":"0.00000648","type":"SPOT","open":6.59e-06,"volume":"3028.99","sell":"0.00000659","buy":"0.00000644","at":1610177490,"name":"BAT/BTC"},"ltcbtc":{"base_unit":"ltc","quote_unit":"btc","low":"0.004127","high":"0.004321","last":"0.004245","type":"SPOT","open":0.004187,"volume":"25.234","sell":"0.004232","buy":"0.004199","at":1610177490,"name":"LTC/BTC"},"qkcbtc":{"base_unit":"qkc","quote_unit":"btc","low":"0.00000013","high":"0.00000019","last":"0.00000018","type":"SPOT","open":1.6e-07,"volume":"200740.0","sell":"0.00000018","buy":"0.00000016","at":1610177490,"name":"QKC/BTC"},"npxsbtc":{"base_unit":"npxs","quote_unit":"btc","low":"0.00000001","high":"0.00000002","last":"0.00000001","type":"SPOT","open":1.0e-08,"volume":"166956012.0","sell":"0.00000002","buy":"0.00000001","at":1610177490,"name":"NPXS/BTC"},"dashbtc":{"base_unit":"dash","quote_unit":"btc","low":"0.002335","high":"0.002515","last":"0.002438","type":"SPOT","open":0.002503,"volume":"5.17","sell":"0.002493","buy":"0.002428","at":1610177490,"name":"DASH/BTC"},"funbtc":{"base_unit":"fun","quote_unit":"btc","low":"0.00000026","high":"0.00000033","last":"0.00000029","type":"SPOT","open":3.0e-07,"volume":"30492.0","sell":"0.0000003","buy":"0.00000029","at":1610177490,"name":"FUN/BTC"},"iostbtc":{"base_unit":"iost","quote_unit":"btc","low":"0.00000016","high":"0.0000003","last":"0.00000029","type":"SPOT","open":1.7e-07,"volume":"1499894.0","sell":"0.00000029","buy":"0.00000026","at":1610177490,"name":"IOST/BTC"},"nulsbtc":{"base_unit":"nuls","quote_unit":"btc","low":"0.00000603","high":"0.00000662","last":"0.00000662","type":"SPOT","open":6.42e-06,"volume":"3321.0","sell":"0.00000662","buy":"0.00000647","at":1610177490,"name":"NULS/BTC"},"omgbtc":{"base_unit":"omg","quote_unit":"btc","low":"0.000084","high":"0.000088","last":"0.000087","type":"SPOT","open":8.8e-05,"volume":"107.87","sell":"0.000087","buy":"0.000084","at":1610177490,"name":"OMG/BTC"},"poebtc":{"base_unit":"poe","quote_unit":"btc","low":"0.00000005","high":"0.00000005","last":"0.00000005","type":"SPOT","open":5.0e-08,"volume":"0.0","sell":"0.00000005","buy":"0.00000002","at":1610177490,"name":"POE/BTC"},"reqbtc":{"base_unit":"req","quote_unit":"btc","low":"0.00000064","high":"0.00000077","last":"0.00000072","type":"SPOT","open":7.0e-07,"volume":"292361.0","sell":"0.00000076","buy":"0.00000069","at":1610177490,"name":"REQ/BTC"},"sntbtc":{"base_unit":"snt","quote_unit":"btc","low":"0.00000139","high":"0.00000157","last":"0.00000147","type":"SPOT","open":1.57e-06,"volume":"4117.0","sell":"0.00000147","buy":"0.00000141","at":1610177490,"name":"SNT/BTC"},"thetabtc":{"base_unit":"theta","quote_unit":"btc","low":"0.00004652","high":"0.00005003","last":"0.00004784","type":"SPOT","open":4.869e-05,"volume":"190.0","sell":"0.00005057","buy":"0.00004984","at":1610177490,"name":"THETA/BTC"},"zrxbtc":{"base_unit":"zrx","quote_unit":"btc","low":"0.00001033","high":"0.0000118","last":"0.00001128","type":"SPOT","open":1.133e-05,"volume":"1826.05","sell":"0.00001172","buy":"0.00001118","at":1610177490,"name":"ZRX/BTC"},"eosbtc":{"base_unit":"eos","quote_unit":"btc","low":"0.0000747","high":"0.0000815","last":"0.0000761","type":"SPOT","open":8.03e-05,"volume":"136.11","sell":"0.000079","buy":"0.000077","at":1610177490,"name":"EOS/BTC"},"icxbtc":{"base_unit":"icx","quote_unit":"btc","low":"0.0000147","high":"0.0000161","last":"0.000016","type":"SPOT","open":1.49e-05,"volume":"2680.88","sell":"0.0000163","buy":"0.0000157","at":1610177490,"name":"ICX/BTC"},"hotbtc":{"base_unit":"hot","quote_unit":"btc","low":"0.00000002","high":"0.00000003","last":"0.00000003","type":"SPOT","open":2.0e-08,"volume":"472912.0","sell":"0.00000003","buy":"0.00000002","at":1610177490,"name":"HOT/BTC"},"polybtc":{"base_unit":"poly","quote_unit":"btc","low":"0.00000239","high":"0.0000027","last":"0.00000245","type":"SPOT","open":2.55e-06,"volume":"5359.0","sell":"0.0000025","buy":"0.00000245","at":1610177490,"name":"POLY/BTC"},"paxbtc":{"base_unit":"pax","quote_unit":"btc","low":"0.0","high":"0.0","last":"0.0","type":"SPOT","open":"0.0","volume":"0.0","sell":"0.0","buy":"0.00000001","at":1610177490,"name":"PAX/BTC"},"usdcbtc":{"base_unit":"usdc","quote_unit":"btc","low":"0.0","high":"0.0","last":"0.0","type":"SPOT","open":"0.0","volume":"0.0","sell":"0.0","buy":"0.0","at":1610177490,"name":"USDC/BTC"},"xlmbtc":{"base_unit":"xlm","quote_unit":"btc","low":"0.0","high":"0.0","last":"0.0","type":"SPOT","open":"0.0","volume":"0.0","sell":"0.0","buy":"0.00000001","at":1610177490,"name":"XLM/BTC"},"bttbtc":{"base_unit":"btt","quote_unit":"btc","low":"0.00000001","high":"0.00000002","last":"0.00000001","type":"SPOT","open":1.0e-08,"volume":"9139018.0","sell":"0.00000002","buy":"0.00000001","at":1610177490,"name":"BTT/BTC"},"fetbtc":{"base_unit":"fet","quote_unit":"btc","low":"0.00000172","high":"0.00000196","last":"0.00000192","type":"SPOT","open":1.65e-06,"volume":"3821.0","sell":"0.000002","buy":"0.00000191","at":1610177490,"name":"FET/BTC"},"celrbtc":{"base_unit":"celr","quote_unit":"btc","low":"0.00000015","high":"0.0000002","last":"0.0000002","type":"SPOT","open":1.7e-07,"volume":"103103.0","sell":"0.0000002","buy":"0.00000018","at":1610177490,"name":"CELR/BTC"},"maticbtc":{"base_unit":"matic","quote_unit":"btc","low":"0.00000074","high":"0.00000084","last":"0.00000079","type":"SPOT","open":8.2e-07,"volume":"114820.6","sell":"0.00000081","buy":"0.00000078","at":1610177490,"name":"MATIC/BTC"},"adabtc":{"base_unit":"ada","quote_unit":"btc","low":"0.00000715","high":"0.00000796","last":"0.00000773","type":"SPOT","open":7.37e-06,"volume":"31863.2","sell":"0.00000771","buy":"0.00000761","at":1610177490,"name":"ADA/BTC"},"rvnbtc":{"base_unit":"rvn","quote_unit":"btc","low":"0.00000037","high":"0.00000042","last":"0.00000042","type":"SPOT","open":3.9e-07,"volume":"56461.0","sell":"0.00000042","buy":"0.00000041","at":1610177490,"name":"RVN/BTC"},"xmrbtc":{"base_unit":"xmr","quote_unit":"btc","low":"0.003489","high":"0.003775","last":"0.003491","type":"SPOT","open":0.003732,"volume":"2.836","sell":"0.003614","buy":"0.00357","at":1610177490,"name":"XMR/BTC"},"atombtc":{"base_unit":"atom","quote_unit":"btc","low":"0.0001454","high":"0.00016","last":"0.000158","type":"SPOT","open":0.0001571,"volume":"145.47","sell":"0.0001599","buy":"0.000158","at":1610177490,"name":"ATOM/BTC"},"bnbbtc":{"base_unit":"bnb","quote_unit":"btc","low":"0.0010233","high":"0.0011086","last":"0.0010645","type":"SPOT","open":0.0010798,"volume":"100.26","sell":"0.0010643","buy":"0.0010601","at":1610177490,"name":"BNB/BTC"},"wrxbtc":{"base_unit":"wrx","quote_unit":"btc","low":"0.00000197","high":"0.00000226","last":"0.00000226","type":"SPOT","open":2.15e-06,"volume":"46160.0","sell":"0.00000229","buy":"0.00000221","at":1610177490,"name":"WRX/BTC"},"fttbtc":{"base_unit":"ftt","quote_unit":"btc","low":"0.000225","high":"0.0002369","last":"0.000225","type":"SPOT","open":0.000234,"volume":"33.163","sell":"0.0002262","buy":"0.0002229","at":1610177490,"name":"FTT/BTC"},"stmxbtc":{"base_unit":"stmx","quote_unit":"btc","low":"0.00000006","high":"0.00000008","last":"0.00000008","type":"SPOT","open":7.0e-08,"volume":"96386.0","sell":"0.00000008","buy":"0.00000006","at":1610177490,"name":"STMX/BTC"},"glmbtc":{"base_unit":"glm","quote_unit":"btc","low":"0.0","high":"0.0","last":"0.0","type":"SPOT","open":"0.0","volume":"0.0","sell":"0.0","buy":"0.0","at":1610177490,"name":"GLM/BTC"},"btcusdt":{"base_unit":"btc","quote_unit":"usdt","low":"38360.0","high":"41974.0","last":"39490.0","type":"SPOT","open":38833.0,"volume":"43.3792","sell":"39600.0","buy":"39490.0","at":1610177490,"name":"BTC/USDT"},"trxusdt":{"base_unit":"trx","quote_unit":"usdt","low":"0.02935","high":"0.03133","last":"0.03079","type":"SPOT","open":0.03029,"volume":"4742279.0","sell":"0.03078","buy":"0.03059","at":1610177490,"name":"TRX/USDT"},"xrpusdt":{"base_unit":"xrp","quote_unit":"usdt","low":"0.30001","high":"0.345","last":"0.31572","type":"SPOT","open":0.31357,"volume":"1923287.0","sell":"0.3165","buy":"0.31572","at":1610177490,"name":"XRP/USDT"},"eosusdt":{"base_unit":"eos","quote_unit":"usdt","low":"2.9952","high":"3.2385","last":"3.0628","type":"SPOT","open":3.0981,"volume":"13192.44","sell":"3.0816","buy":"3.0591","at":1610177490,"name":"EOS/USDT"},"ethusdt":{"base_unit":"eth","quote_unit":"usdt","low":"1153.64","high":"1270.0","last":"1195.69","type":"SPOT","open":1188.15,"volume":"1017.99","sell":"1197.1","buy":"1195.69","at":1610177490,"name":"ETH/USDT"},"icxusdt":{"base_unit":"icx","quote_unit":"usdt","low":"0.5747","high":"0.6414","last":"0.6283","type":"SPOT","open":0.5626,"volume":"20523.12","sell":"0.629","buy":"0.6277","at":1610177490,"name":"ICX/USDT"},"ltcusdt":{"base_unit":"ltc","quote_unit":"usdt","low":"162.13","high":"181.47","last":"166.34","type":"SPOT","open":161.03,"volume":"1349.981","sell":"166.66","buy":"165.58","at":1610177490,"name":"LTC/USDT"},"tusdusdt":{"base_unit":"tusd","quote_unit":"usdt","low":"0.9946","high":"1.0017","last":"0.9946","type":"SPOT","open":1.0017,"volume":"7.0","sell":"1.0033","buy":"0.9956","at":1610177490,"name":"TUSD/USDT"},"npxsusdt":{"base_unit":"npxs","quote_unit":"usdt","low":"0.000185","high":"0.000587","last":"0.000456","type":"SPOT","open":0.000186,"volume":"706110236.0","sell":"0.000456","buy":"0.000451","at":1610177490,"name":"NPXS/USDT"},"hotusdt":{"base_unit":"hot","quote_unit":"usdt","low":"0.00077","high":"0.0009317","last":"0.0008742","type":"SPOT","open":0.00077,"volume":"10717689.0","sell":"0.0008911","buy":"0.0008783","at":1610177490,"name":"HOT/USDT"},"batusdt":{"base_unit":"bat","quote_unit":"usdt","low":"0.2418","high":"0.2662","last":"0.2572","type":"SPOT","open":0.2598,"volume":"162856.95","sell":"0.2594","buy":"0.2575","at":1610177490,"name":"BAT/USDT"},"dashusdt":{"base_unit":"dash","quote_unit":"usdt","low":"94.84","high":"100.43","last":"97.48","type":"SPOT","open":95.54,"volume":"230.974","sell":"97.54","buy":"96.93","at":1610177490,"name":"DASH/USDT"},"ncashusdt":{"base_unit":"ncash","quote_unit":"usdt","low":"0.0009","high":"0.0013","last":"0.000992","type":"SPOT","open":0.000941,"volume":"103525759.0","sell":"0.000995","buy":"0.000992","at":1610177491,"name":"NCASH/USDT"},"qkcusdt":{"base_unit":"qkc","quote_unit":"usdt","low":"0.00554","high":"0.00748","last":"0.00672","type":"SPOT","open":0.0058,"volume":"2609209.0","sell":"0.00673","buy":"0.00631","at":1610177491,"name":"QKC/USDT"},"zilusdt":{"base_unit":"zil","quote_unit":"usdt","low":"0.07127","high":"0.077","last":"0.07175","type":"SPOT","open":0.07487,"volume":"773635.0","sell":"0.07259","buy":"0.07172","at":1610177491,"name":"ZIL/USDT"},"zrxusdt":{"base_unit":"zrx","quote_unit":"usdt","low":"0.425","high":"0.4615","last":"0.4502","type":"SPOT","open":0.4298,"volume":"12042.82","sell":"0.4547","buy":"0.4506","at":1610177491,"name":"ZRX/USDT"},"bchusdt":{"base_unit":"bch","quote_unit":"usdt","low":"418.82","high":"453.3","last":"424.93","type":"SPOT","open":429.89,"volume":"202.164","sell":"426.15","buy":"422.7","at":1610177491,"name":"BCH/USDT"},"bchsvusdt":{"base_unit":"bchsv","quote_unit":"usdt","low":"170.1","high":"183.68","last":"183.0","type":"SPOT","open":179.01,"volume":"17.371","sell":"183.0","buy":"176.5","at":1610177491,"name":"BCHSV/USDT"},"paxusdt":{"base_unit":"pax","quote_unit":"usdt","low":"0.9941","high":"1.0019","last":"0.9952","type":"SPOT","open":1.0019,"volume":"3429.25","sell":"0.995","buy":"0.9947","at":1610177491,"name":"PAX/USDT"},"usdcusdt":{"base_unit":"usdc","quote_unit":"usdt","low":"0.996","high":"1.002","last":"1.001","type":"SPOT","open":1.002,"volume":"8747.09","sell":"1.001","buy":"0.996","at":1610177491,"name":"USDC/USDT"},"omgusdt":{"base_unit":"omg","quote_unit":"usdt","low":"3.2291","high":"3.5555","last":"3.4199","type":"SPOT","open":3.4097,"volume":"3685.23","sell":"3.4","buy":"3.3695","at":1610177491,"name":"OMG/USDT"},"polyusdt":{"base_unit":"poly","quote_unit":"usdt","low":"0.096","high":"0.1077","last":"0.0975","type":"SPOT","open":0.1,"volume":"53154.0","sell":"0.0972","buy":"0.0964","at":1610177491,"name":"POLY/USDT"},"dentusdt":{"base_unit":"dent","quote_unit":"usdt","low":"0.000233","high":"0.000423","last":"0.00037","type":"SPOT","open":0.000235,"volume":"266510771.0","sell":"0.000379","buy":"0.00037","at":1610177491,"name":"DENT/USDT"},"iostusdt":{"base_unit":"iost","quote_unit":"usdt","low":"0.00634","high":"0.0123","last":"0.01102","type":"SPOT","open":0.00627,"volume":"16917549.0","sell":"0.01109","buy":"0.01102","at":1610177491,"name":"IOST/USDT"},"funusdt":{"base_unit":"fun","quote_unit":"usdt","low":"0.01081","high":"0.014","last":"0.011022","type":"SPOT","open":0.011881,"volume":"4580224.0","sell":"0.011882","buy":"0.011216","at":1610177491,"name":"FUN/USDT"},"poeusdt":{"base_unit":"poe","quote_unit":"usdt","low":"0.000709","high":"0.000709","last":"0.000709","type":"SPOT","open":0.000709,"volume":"0.0","sell":"0.000828","buy":"0.000504","at":1610177491,"name":"POE/USDT"},"sntusdt":{"base_unit":"snt","quote_unit":"usdt","low":"0.056","high":"0.06649","last":"0.056","type":"SPOT","open":0.0633,"volume":"49196.0","sell":"0.05832","buy":"0.056","at":1610177491,"name":"SNT/USDT"},"thetausdt":{"base_unit":"theta","quote_unit":"usdt","low":"1.85","high":"2.02692","last":"1.9757","type":"SPOT","open":1.96373,"volume":"11821.0","sell":"1.99124","buy":"1.97575","at":1610177491,"name":"THETA/USDT"},"requsdt":{"base_unit":"req","quote_unit":"usdt","low":"0.02626","high":"0.02938","last":"0.02771","type":"SPOT","open":0.02631,"volume":"246217.0","sell":"0.02894","buy":"0.02779","at":1610177491,"name":"REQ/USDT"},"xlmusdt":{"base_unit":"xlm","quote_unit":"usdt","low":"0.27894","high":"0.3289","last":"0.2874","type":"SPOT","open":0.31297,"volume":"1524686.4","sell":"0.288","buy":"0.2874","at":1610177491,"name":"XLM/USDT"},"xtzusdt":{"base_unit":"xtz","quote_unit":"usdt","low":"2.35","high":"2.5575","last":"2.4329","type":"SPOT","open":2.3764,"volume":"3934.1","sell":"2.4727","buy":"2.4523","at":1610177491,"name":"XTZ/USDT"},"bttusdt":{"base_unit":"btt","quote_unit":"usdt","low":"0.000321","high":"0.0005279","last":"0.0004142","type":"SPOT","open":0.0003232,"volume":"231820465.0","sell":"0.0004128","buy":"0.0004112","at":1610177491,"name":"BTT/USDT"},"fetusdt":{"base_unit":"fet","quote_unit":"usdt","low":"0.0683","high":"0.0809","last":"0.077","type":"SPOT","open":0.07,"volume":"464820.0","sell":"0.078","buy":"0.0772","at":1610177491,"name":"FET/USDT"},"tfuelusdt":{"base_unit":"tfuel","quote_unit":"usdt","low":"0.02551","high":"0.0282","last":"0.02636","type":"SPOT","open":0.0275,"volume":"901909.0","sell":"0.02652","buy":"0.02618","at":1610177491,"name":"TFUEL/USDT"},"celrusdt":{"base_unit":"celr","quote_unit":"usdt","low":"0.00638","high":"0.0083","last":"0.00748","type":"SPOT","open":0.00638,"volume":"2095201.0","sell":"0.0075","buy":"0.00743","at":1610177491,"name":"CELR/USDT"},"maticusdt":{"base_unit":"matic","quote_unit":"usdt","low":"0.03069","high":"0.035","last":"0.03105","type":"SPOT","open":0.03152,"volume":"3468838.8","sell":"0.03134","buy":"0.03104","at":1610177491,"name":"MATIC/USDT"},"adausdt":{"base_unit":"ada","quote_unit":"usdt","low":"0.28657","high":"0.32022","last":"0.3023","type":"SPOT","open":0.30788,"volume":"531327.7","sell":"0.30231","buy":"0.301","at":1610177491,"name":"ADA/USDT"},"rvnusdt":{"base_unit":"rvn","quote_unit":"usdt","low":"0.01502","high":"0.01784","last":"0.01645","type":"SPOT","open":0.01513,"volume":"277950.0","sell":"0.01682","buy":"0.01656","at":1610177491,"name":"RVN/USDT"},"xmrusdt":{"base_unit":"xmr","quote_unit":"usdt","low":"140.0","high":"150.04","last":"142.43","type":"SPOT","open":146.25,"volume":"47.948","sell":"142.33","buy":"141.31","at":1610177491,"name":"XMR/USDT"},"atomusdt":{"base_unit":"atom","quote_unit":"usdt","low":"5.718","high":"6.601","last":"6.209","type":"SPOT","open":6.12,"volume":"12748.43","sell":"6.318","buy":"6.25","at":1610177491,"name":"ATOM/USDT"},"algousdt":{"base_unit":"algo","quote_unit":"usdt","low":"0.43","high":"0.486","last":"0.454","type":"SPOT","open":0.43,"volume":"32710.242","sell":"0.467","buy":"0.462","at":1610177491,"name":"ALGO/USDT"},"linkusdt":{"base_unit":"link","quote_unit":"usdt","low":"14.64","high":"16.2347","last":"15.0926","type":"SPOT","open":15.0963,"volume":"4289.36","sell":"15.3944","buy":"15.303","at":1610177491,"name":"LINK/USDT"},"qtumusdt":{"base_unit":"qtum","quote_unit":"usdt","low":"2.8","high":"3.036","last":"2.915","type":"SPOT","open":2.77,"volume":"1322.256","sell":"2.917","buy":"2.883","at":1610177491,"name":"QTUM/USDT"},"etcusdt":{"base_unit":"etc","quote_unit":"usdt","low":"6.7","high":"7.1494","last":"6.7512","type":"SPOT","open":6.8876,"volume":"1398.92","sell":"6.796","buy":"6.7484","at":1610177491,"name":"ETC/USDT"},"iotausdt":{"base_unit":"iota","quote_unit":"usdt","low":"0.351","high":"0.445","last":"0.4154","type":"SPOT","open":0.351,"volume":"24264.6","sell":"0.4209","buy":"0.4152","at":1610177491,"name":"IOTA/USDT"},"zecusdt":{"base_unit":"zec","quote_unit":"usdt","low":"65.25","high":"69.74","last":"66.88","type":"SPOT","open":66.46,"volume":"229.957","sell":"66.97","buy":"66.5","at":1610177491,"name":"ZEC/USDT"},"wavesusdt":{"base_unit":"waves","quote_unit":"usdt","low":"5.4679","high":"5.923","last":"5.5751","type":"SPOT","open":5.5983,"volume":"1626.45","sell":"5.6002","buy":"5.5442","at":1610177491,"name":"WAVES/USDT"},"ftmusdt":{"base_unit":"ftm","quote_unit":"usdt","low":"0.02337","high":"0.0272","last":"0.02538","type":"SPOT","open":0.02303,"volume":"467460.1","sell":"0.02558","buy":"0.02539","at":1610177491,"name":"FTM/USDT"},"enjusdt":{"base_unit":"enj","quote_unit":"usdt","low":"0.18939","high":"0.27564","last":"0.19549","type":"SPOT","open":0.24423,"volume":"311367.9","sell":"0.1971","buy":"0.19495","at":1610177491,"name":"ENJ/USDT"},"lskusdt":{"base_unit":"lsk","quote_unit":"usdt","low":"1.272","high":"1.4212","last":"1.3654","type":"SPOT","open":1.2273,"volume":"2212.01","sell":"1.41","buy":"1.3899","at":1610177491,"name":"LSK/USDT"},"steemusdt":{"base_unit":"steem","quote_unit":"usdt","low":"0.1751","high":"0.192","last":"0.1851","type":"SPOT","open":0.1746,"volume":"15005.66","sell":"0.187","buy":"0.1829","at":1610177491,"name":"STEEM/USDT"},"xvgusdt":{"base_unit":"xvg","quote_unit":"usdt","low":"0.01357","high":"0.0168","last":"0.01389","type":"SPOT","open":0.014,"volume":"1662647.0","sell":"0.0141","buy":"0.01388","at":1610177491,"name":"XVG/USDT"},"loomusdt":{"base_unit":"loom","quote_unit":"usdt","low":"0.04403","high":"0.0525","last":"0.04403","type":"SPOT","open":0.04943,"volume":"142749.0","sell":"0.04479","buy":"0.04402","at":1610177491,"name":"LOOM/USDT"},"manausdt":{"base_unit":"mana","quote_unit":"usdt","low":"0.11038","high":"0.14778","last":"0.113","type":"SPOT","open":0.14582,"volume":"228038.0","sell":"0.113","buy":"0.1125","at":1610177491,"name":"MANA/USDT"},"repusdt":{"base_unit":"rep","quote_unit":"usdt","low":"17.875","high":"19.275","last":"18.151","type":"SPOT","open":18.216,"volume":"24.412","sell":"18.237","buy":"17.979","at":1610177491,"name":"REP/USDT"},"blzusdt":{"base_unit":"blz","quote_unit":"usdt","low":"0.07292","high":"0.08285","last":"0.08","type":"SPOT","open":0.07308,"volume":"290979.0","sell":"0.08","buy":"0.07836","at":1610177491,"name":"BLZ/USDT"},"xzcusdt":{"base_unit":"xzc","quote_unit":"usdt","low":"3.298","high":"4.1","last":"3.61","type":"SPOT","open":3.26,"volume":"13070.71","sell":"3.679","buy":"3.619","at":1610177491,"name":"XZC/USDT"},"nanousdt":{"base_unit":"nano","quote_unit":"usdt","low":"3.6","high":"4.75","last":"3.988","type":"SPOT","open":3.7017,"volume":"29545.85","sell":"4.056","buy":"3.9245","at":1610177491,"name":"NANO/USDT"},"scusdt":{"base_unit":"sc","quote_unit":"usdt","low":"0.00458","high":"0.00504","last":"0.00489","type":"SPOT","open":0.00486,"volume":"3434406.0","sell":"0.0049","buy":"0.00481","at":1610177491,"name":"SC/USDT"},"btgusdt":{"base_unit":"btg","quote_unit":"usdt","low":"10.2","high":"11.66","last":"10.5","type":"SPOT","open":11.01,"volume":"641.49","sell":"10.72","buy":"10.6","at":1610177491,"name":"BTG/USDT"},"xemusdt":{"base_unit":"xem","quote_unit":"usdt","low":"0.2209","high":"0.2678","last":"0.2269","type":"SPOT","open":0.2323,"volume":"746415.0","sell":"0.2271","buy":"0.2231","at":1610177491,"name":"XEM/USDT"},"btsusdt":{"base_unit":"bts","quote_unit":"usdt","low":"0.027","high":"0.03","last":"0.02798","type":"SPOT","open":0.02678,"volume":"165797.0","sell":"0.02843","buy":"0.02796","at":1610177491,"name":"BTS/USDT"},"ardrusdt":{"base_unit":"ardr","quote_unit":"usdt","low":"0.07925","high":"0.08602","last":"0.08007","type":"SPOT","open":0.0807,"volume":"7956.0","sell":"0.08385","buy":"0.07974","at":1610177491,"name":"ARDR/USDT"},"nasusdt":{"base_unit":"nas","quote_unit":"usdt","low":"0.281","high":"0.3133","last":"0.3097","type":"SPOT","open":0.2673,"volume":"5054.33","sell":"0.313","buy":"0.3016","at":1610177491,"name":"NAS/USDT"},"winusdt":{"base_unit":"win","quote_unit":"usdt","low":"0.0000738","high":"0.0000955","last":"0.0000854","type":"SPOT","open":7.46e-05,"volume":"254834526.0","sell":"0.0000857","buy":"0.000085","at":1610177491,"name":"WIN/USDT"},"bnbusdt":{"base_unit":"bnb","quote_unit":"usdt","low":"41.1912","high":"43.3666","last":"42.0698","type":"SPOT","open":42.0063,"volume":"785.28","sell":"42.082","buy":"41.8905","at":1610177491,"name":"BNB/USDT"},"chzusdt":{"base_unit":"chz","quote_unit":"usdt","low":"0.018733","high":"0.020308","last":"0.019234","type":"SPOT","open":0.018939,"volume":"169637.0","sell":"0.019503","buy":"0.019241","at":1610177491,"name":"CHZ/USDT"},"wrxusdt":{"base_unit":"wrx","quote_unit":"usdt","low":"0.07893","high":"0.08946","last":"0.08933","type":"SPOT","open":0.08127,"volume":"1487086.0","sell":"0.08933","buy":"0.08875","at":1610177491,"name":"WRX/USDT"},"kavausdt":{"base_unit":"kava","quote_unit":"usdt","low":"1.543","high":"1.823","last":"1.8007","type":"SPOT","open":1.5776,"volume":"11863.48","sell":"1.8113","buy":"1.7904","at":1610177491,"name":"KAVA/USDT"},"ankrusdt":{"base_unit":"ankr","quote_unit":"usdt","low":"0.008572","high":"0.009808","last":"0.009235","type":"SPOT","open":0.008736,"volume":"6005361.0","sell":"0.009341","buy":"0.009241","at":1610177491,"name":"ANKR/USDT"},"busdusdt":{"base_unit":"busd","quote_unit":"usdt","low":"0.9962","high":"1.005","last":"0.9966","type":"SPOT","open":1.0005,"volume":"27052.94","sell":"0.9999","buy":"0.9966","at":1610177491,"name":"BUSD/USDT"},"oneusdt":{"base_unit":"one","quote_unit":"usdt","low":"0.00603","high":"0.00897","last":"0.00774","type":"SPOT","open":0.00596,"volume":"8513530.0","sell":"0.00776","buy":"0.00775","at":1610177491,"name":"ONE/USDT"},"ognusdt":{"base_unit":"ogn","quote_unit":"usdt","low":"0.0","high":"0.0","last":"0.0","type":"SPOT","open":"0.0","volume":"0.0","sell":"0.0","buy":"0.0","at":1610177491,"name":"OGN/USDT"},"hiveusdt":{"base_unit":"hive","quote_unit":"usdt","low":"0.1143","high":"0.1313","last":"0.1275","type":"SPOT","open":0.1143,"volume":"48140.3","sell":"0.1273","buy":"0.1233","at":1610177491,"name":"HIVE/USDT"},"fttusdt":{"base_unit":"ftt","quote_unit":"usdt","low":"8.702","high":"9.62","last":"8.831","type":"SPOT","open":8.888,"volume":"223.089","sell":"8.897","buy":"8.823","at":1610177491,"name":"FTT/USDT"},"bandusdt":{"base_unit":"band","quote_unit":"usdt","low":"8.5643","high":"11.1963","last":"10.8993","type":"SPOT","open":8.8812,"volume":"12564.11","sell":"10.8993","buy":"10.872","at":1610177491,"name":"BAND/USDT"},"jstusdt":{"base_unit":"jst","quote_unit":"usdt","low":"0.02591","high":"0.02925","last":"0.02637","type":"SPOT","open":0.02552,"volume":"247121.0","sell":"0.02651","buy":"0.026","at":1610177491,"name":"JST/USDT"},"ctsiusdt":{"base_unit":"ctsi","quote_unit":"usdt","low":"0.045","high":"0.05467","last":"0.05364","type":"SPOT","open":0.04552,"volume":"301082.5","sell":"0.05417","buy":"0.05362","at":1610177491,"name":"CTSI/USDT"},"chrusdt":{"base_unit":"chr","quote_unit":"usdt","low":"0.0243","high":"0.02883","last":"0.02719","type":"SPOT","open":0.02426,"volume":"749597.0","sell":"0.02725","buy":"0.02719","at":1610177491,"name":"CHR/USDT"},"tomousdt":{"base_unit":"tomo","quote_unit":"usdt","low":"0.9112","high":"1.2276","last":"1.2152","type":"SPOT","open":0.9163,"volume":"35661.05","sell":"1.2245","buy":"1.0","at":1610177491,"name":"TOMO/USDT"},"stxusdt":{"base_unit":"stx","quote_unit":"usdt","low":"0.0","high":"0.0","last":"0.0","type":"SPOT","open":"0.0","volume":"0.0","sell":"0.0","buy":"0.0","at":1610177491,"name":"STX/USDT"},"stmxusdt":{"base_unit":"stmx","quote_unit":"usdt","low":"0.002447","high":"0.003173","last":"0.002786","type":"SPOT","open":0.002476,"volume":"2468730.0","sell":"0.002895","buy":"0.002778","at":1610177491,"name":"STMX/USDT"},"gxsusdt":{"base_unit":"gxs","quote_unit":"usdt","low":"0.3141","high":"0.3396","last":"0.3328","type":"SPOT","open":0.3076,"volume":"2700.55","sell":"0.3329","buy":"0.3312","at":1610177491,"name":"GXS/USDT"},"mdtusdt":{"base_unit":"mdt","quote_unit":"usdt","low":"0.0","high":"0.0","last":"0.0","type":"SPOT","open":"0.0","volume":"0.0","sell":"0.0","buy":"0.0","at":1610177491,"name":"MDT/USDT"},"ltousdt":{"base_unit":"lto","quote_unit":"usdt","low":"0.0","high":"0.0","last":"0.0","type":"SPOT","open":"0.0","volume":"0.0","sell":"0.0","buy":"0.0","at":1610177491,"name":"LTO/USDT"},"lrcusdt":{"base_unit":"lrc","quote_unit":"usdt","low":"0.34","high":"0.42576","last":"0.4128","type":"SPOT","open":0.35087,"volume":"178248.0","sell":"0.41876","buy":"0.4141","at":1610177491,"name":"LRC/USDT"},"dogeusdt":{"base_unit":"doge","quote_unit":"usdt","low":"0.0091748","high":"0.010227","last":"0.0099893","type":"SPOT","open":0.0095685,"volume":"5266872.0","sell":"0.0100768","buy":"0.0099893","at":1610177491,"name":"DOGE/USDT"},"neousdt":{"base_unit":"neo","quote_unit":"usdt","low":"19.0","high":"21.253","last":"19.702","type":"SPOT","open":19.99,"volume":"747.395","sell":"19.929","buy":"19.78","at":1610177491,"name":"NEO/USDT"},"hbarusdt":{"base_unit":"hbar","quote_unit":"usdt","low":"0.0","high":"0.0","last":"0.0","type":"SPOT","open":"0.0","volume":"0.0","sell":"0.0","buy":"0.0","at":1610177491,"name":"HBAR/USDT"},"storjusdt":{"base_unit":"storj","quote_unit":"usdt","low":"0.3435","high":"0.414","last":"0.3651","type":"SPOT","open":0.3345,"volume":"46944.0","sell":"0.367","buy":"0.3631","at":1610177491,"name":"STORJ/USDT"},"compusdt":{"base_unit":"comp","quote_unit":"usdt","low":"158.0","high":"177.33","last":"166.5","type":"SPOT","open":163.32,"volume":"83.462","sell":"166.5","buy":"164.58","at":1610177491,"name":"COMP/USDT"},"cotiusdt":{"base_unit":"coti","quote_unit":"usdt","low":"0.05463","high":"0.062","last":"0.05887","type":"SPOT","open":0.05463,"volume":"273611.1","sell":"0.05896","buy":"0.0585","at":1610177491,"name":"COTI/USDT"},"dgbusdt":{"base_unit":"dgb","quote_unit":"usdt","low":"0.02882","high":"0.03236","last":"0.03026","type":"SPOT","open":0.03,"volume":"166095.0","sell":"0.03059","buy":"0.03024","at":1610177491,"name":"DGB/USDT"},"grsusdt":{"base_unit":"grs","quote_unit":"usdt","low":"0.3625","high":"0.4147","last":"0.367","type":"SPOT","open":0.398,"volume":"20699.0","sell":"0.367","buy":"0.3661","at":1610177491,"name":"GRS/USDT"},"snxusdt":{"base_unit":"snx","quote_unit":"usdt","low":"10.835","high":"12.887","last":"11.294","type":"SPOT","open":12.502,"volume":"1301.219","sell":"11.409","buy":"11.277","at":1610177491,"name":"SNX/USDT"},"renusdt":{"base_unit":"ren","quote_unit":"usdt","low":"0.3513","high":"0.4112","last":"0.38099","type":"SPOT","open":0.37093,"volume":"6349.0","sell":"0.39107","buy":"0.38671","at":1610177491,"name":"REN/USDT"},"sxpusdt":{"base_unit":"sxp","quote_unit":"usdt","low":"0.841","high":"1.099","last":"1.022","type":"SPOT","open":0.864,"volume":"312091.69","sell":"1.026","buy":"1.019","at":1610177491,"name":"SXP/USDT"},"mkrusdt":{"base_unit":"mkr","quote_unit":"usdt","low":"1012.7","high":"1113.51","last":"1049.58","type":"SPOT","open":1055.53,"volume":"2.27802","sell":"1069.61","buy":"1059.19","at":1610177491,"name":"MKR/USDT"},"daiusdt":{"base_unit":"dai","quote_unit":"usdt","low":"0.0","high":"0.0","last":"0.0","type":"SPOT","open":"0.0","volume":"0.0","sell":"0.0","buy":"0.0","at":1610177491,"name":"DAI/USDT"},"avausdt":{"base_unit":"ava","quote_unit":"usdt","low":"0.9081","high":"1.0494","last":"1.0229","type":"SPOT","open":0.8813,"volume":"7339.9","sell":"1.0494","buy":"1.0217","at":1610177491,"name":"AVA/USDT"},"balusdt":{"base_unit":"bal","quote_unit":"usdt","low":"0.0","high":"0.0","last":"0.0","type":"SPOT","open":"0.0","volume":"0.0","sell":"0.0","buy":"0.0","at":1610177491,"name":"BAL/USDT"},"srmusdt":{"base_unit":"srm","quote_unit":"usdt","low":"1.3071","high":"1.866","last":"1.5268","type":"SPOT","open":1.3071,"volume":"107981.63","sell":"1.569","buy":"1.553","at":1610177491,"name":"SRM/USDT"},"egldusdt":{"base_unit":"egld","quote_unit":"usdt","low":"36.0","high":"40.877","last":"37.111","type":"SPOT","open":38.047,"volume":"882.969","sell":"37.203","buy":"36.788","at":1610177491,"name":"EGLD/USDT"},"cosusdt":{"base_unit":"cos","quote_unit":"usdt","low":"0.0075","high":"0.00806","last":"0.00788","type":"SPOT","open":0.00781,"volume":"541206.9","sell":"0.00798","buy":"0.00786","at":1610177491,"name":"COS/USDT"},"nbsusdt":{"base_unit":"nbs","quote_unit":"usdt","low":"0.01395","high":"0.014859","last":"0.01405","type":"SPOT","open":0.01402,"volume":"75737.0","sell":"0.01405","buy":"0.014","at":1610177491,"name":"NBS/USDT"},"aionusdt":{"base_unit":"aion","quote_unit":"usdt","low":"0.0771","high":"0.0843","last":"0.0836","type":"SPOT","open":0.0779,"volume":"43337.17","sell":"0.0848","buy":"0.0836","at":1610177491,"name":"AION/USDT"},"dotusdt":{"base_unit":"dot","quote_unit":"usdt","low":"9.0","high":"9.7873","last":"9.174","type":"SPOT","open":9.3585,"volume":"8160.87","sell":"9.1883","buy":"9.1173","at":1610177491,"name":"DOT/USDT"},"yfiusdt":{"base_unit":"yfi","quote_unit":"usdt","low":"31000.0","high":"38100.0","last":"37100.0","type":"SPOT","open":31149.62,"volume":"22.121131","sell":"37500.0","buy":"37100.0","at":1610177491,"name":"YFI/USDT"},"iotxusdt":{"base_unit":"iotx","quote_unit":"usdt","low":"0.007033","high":"0.009089","last":"0.008208","type":"SPOT","open":0.007033,"volume":"499130.0","sell":"0.008309","buy":"0.00818","at":1610177491,"name":"IOTX/USDT"},"sandusdt":{"base_unit":"sand","quote_unit":"usdt","low":"0.042","high":"0.047005","last":"0.043904","type":"SPOT","open":0.0455,"volume":"121306.0","sell":"0.044721","buy":"0.044119","at":1610177491,"name":"SAND/USDT"},"uniusdt":{"base_unit":"uni","quote_unit":"usdt","low":"5.6594","high":"6.3527","last":"5.94","type":"SPOT","open":5.9824,"volume":"12583.4","sell":"5.9521","buy":"5.8935","at":1610177491,"name":"UNI/USDT"},"datausdt":{"base_unit":"data","quote_unit":"usdt","low":"0.0472","high":"0.07043","last":"0.05876","type":"SPOT","open":0.04864,"volume":"400449.0","sell":"0.05998","buy":"0.05895","at":1610177491,"name":"DATA/USDT"},"paxgusdt":{"base_unit":"paxg","quote_unit":"usdt","low":"0.0","high":"0.0","last":"0.0","type":"SPOT","open":"0.0","volume":"0.0","sell":"0.0","buy":"0.0","at":1610177491,"name":"PAXG/USDT"},"creamusdt":{"base_unit":"cream","quote_unit":"usdt","low":"75.0","high":"88.5","last":"77.283","type":"SPOT","open":85.0,"volume":"283.382","sell":"77.425","buy":"76.433","at":1610177491,"name":"CREAM/USDT"},"swrvusdt":{"base_unit":"swrv","quote_unit":"usdt","low":"0.0","high":"0.0","last":"0.0","type":"SPOT","open":"0.0","volume":"0.0","sell":"0.0","buy":"0.0","at":1610177491,"name":"SWRV/USDT"},"umausdt":{"base_unit":"uma","quote_unit":"usdt","low":"9.392","high":"10.0","last":"9.49","type":"SPOT","open":9.392,"volume":"256.282","sell":"9.428","buy":"9.296","at":1610177491,"name":"UMA/USDT"},"diausdt":{"base_unit":"dia","quote_unit":"usdt","low":"0.0","high":"0.0","last":"0.0","type":"SPOT","open":"0.0","volume":"0.0","sell":"0.0","buy":"0.0","at":1610177491,"name":"DIA/USDT"},"ksmusdt":{"base_unit":"ksm","quote_unit":"usdt","low":"0.0","high":"0.0","last":"0.0","type":"SPOT","open":"0.0","volume":"0.0","sell":"0.0","buy":"0.0","at":1610177491,"name":"KSM/USDT"},"yfiiusdt":{"base_unit":"yfii","quote_unit":"usdt","low":"1798.16","high":"2028.88","last":"1989.0","type":"SPOT","open":1783.78,"volume":"261.64942","sell":"1989.0","buy":"1981.62","at":1610177491,"name":"YFII/USDT"},"bzrxusdt":{"base_unit":"bzrx","quote_unit":"usdt","low":"0.0","high":"0.0","last":"0.0","type":"SPOT","open":"0.0","volume":"0.0","sell":"0.0","buy":"0.0","at":1610177491,"name":"BZRX/USDT"},"trbusdt":{"base_unit":"trb","quote_unit":"usdt","low":"0.0","high":"0.0","last":"0.0","type":"SPOT","open":"0.0","volume":"0.0","sell":"0.0","buy":"0.0","at":1610177491,"name":"TRB/USDT"},"adxusdt":{"base_unit":"adx","quote_unit":"usdt","low":"0.3579","high":"0.3909","last":"0.3631","type":"SPOT","open":0.3786,"volume":"982.0","sell":"0.3678","buy":"0.3623","at":1610177491,"name":"ADX/USDT"},"aaveusdt":{"base_unit":"aave","quote_unit":"usdt","low":"104.888","high":"117.447","last":"107.897","type":"SPOT","open":108.976,"volume":"144.177","sell":"111.571","buy":"110.191","at":1610177491,"name":"AAVE/USDT"},"filusdt":{"base_unit":"fil","quote_unit":"usdt","low":"21.1839","high":"22.1734","last":"21.7127","type":"SPOT","open":21.8228,"volume":"194.12","sell":"21.7554","buy":"21.42","at":1610177491,"name":"FIL/USDT"},"crvusdt":{"base_unit":"crv","quote_unit":"usdt","low":"0.666","high":"0.75","last":"0.714","type":"SPOT","open":0.661,"volume":"24688.553","sell":"0.724","buy":"0.715","at":1610177491,"name":"CRV/USDT"},"nearusdt":{"base_unit":"near","quote_unit":"usdt","low":"1.4737","high":"1.9542","last":"1.6774","type":"SPOT","open":1.4684,"volume":"3476.151","sell":"1.6989","buy":"1.6749","at":1610177491,"name":"NEAR/USDT"},"hntusdt":{"base_unit":"hnt","quote_unit":"usdt","low":"1.391","high":"1.45","last":"1.437","type":"SPOT","open":1.333,"volume":"1086.933","sell":"1.464","buy":"1.46","at":1610177491,"name":"HNT/USDT"},"avaxusdt":{"base_unit":"avax","quote_unit":"usdt","low":"4.82","high":"6.7644","last":"6.7644","type":"SPOT","open":4.2,"volume":"1387.25","sell":"6.7932","buy":"6.7067","at":1610177491,"name":"AVAX/USDT"},"oxtusdt":{"base_unit":"oxt","quote_unit":"usdt","low":"0.2665","high":"0.2804","last":"0.2794","type":"SPOT","open":0.265,"volume":"8353.2","sell":"0.2696","buy":"0.2665","at":1610177491,"name":"OXT/USDT"},"dockusdt":{"base_unit":"dock","quote_unit":"usdt","low":"0.018772","high":"0.019792","last":"0.018885","type":"SPOT","open":0.019593,"volume":"126660.0","sell":"0.01996","buy":"0.019607","at":1610177491,"name":"DOCK/USDT"},"duskusdt":{"base_unit":"dusk","quote_unit":"usdt","low":"0.055","high":"0.0633","last":"0.0618","type":"SPOT","open":0.0562,"volume":"60246.93","sell":"0.0612","buy":"0.06","at":1610177491,"name":"DUSK/USDT"},"wtcusdt":{"base_unit":"wtc","quote_unit":"usdt","low":"0.3309","high":"0.3446","last":"0.3437","type":"SPOT","open":0.3558,"volume":"1600.81","sell":"0.3424","buy":"0.3412","at":1610177491,"name":"WTC/USDT"},"perlusdt":{"base_unit":"perl","quote_unit":"usdt","low":"0.0","high":"0.0","last":"0.0","type":"SPOT","open":"0.0","volume":"0.0","sell":"0.0","buy":"0.0","at":1610177491,"name":"PERL/USDT"},"straxusdt":{"base_unit":"strax","quote_unit":"usdt","low":"0.469","high":"0.5039","last":"0.5039","type":"SPOT","open":0.4808,"volume":"17667.86","sell":"0.5079","buy":"0.4987","at":1610177491,"name":"STRAX/USDT"},"injusdt":{"base_unit":"inj","quote_unit":"usdt","low":"4.5024","high":"4.948","last":"4.5186","type":"SPOT","open":4.873,"volume":"5404.97","sell":"4.5323","buy":"4.5","at":1610177491,"name":"INJ/USDT"},"vetusdt":{"base_unit":"vet","quote_unit":"usdt","low":"0.0257","high":"0.034412","last":"0.026907","type":"SPOT","open":0.033899,"volume":"3442711.0","sell":"0.026989","buy":"0.026845","at":1610177491,"name":"VET/USDT"},"mtlusdt":{"base_unit":"mtl","quote_unit":"usdt","low":"0.38","high":"0.4179","last":"0.4106","type":"SPOT","open":0.3602,"volume":"410.96","sell":"0.4106","buy":"0.3678","at":1610177491,"name":"MTL/USDT"},"frontusdt":{"base_unit":"front","quote_unit":"usdt","low":"0.32","high":"0.398","last":"0.3556","type":"SPOT","open":0.3313,"volume":"49998.22","sell":"0.3659","buy":"0.3556","at":1610177491,"name":"FRONT/USDT"},"glmusdt":{"base_unit":"glm","quote_unit":"usdt","low":"0.1178","high":"0.1307","last":"0.1233","type":"SPOT","open":0.1277,"volume":"8563.0","sell":"0.1218","buy":"0.1182","at":1610177491,"name":"GLM/USDT"},"sushiusdt":{"base_unit":"sushi","quote_unit":"usdt","low":"3.855","high":"4.476","last":"4.398","type":"SPOT","open":3.961,"volume":"5052.591","sell":"4.49","buy":"4.433","at":1610177491,"name":"SUSHI/USDT"},"ethwrx":{"base_unit":"eth","quote_unit":"wrx","low":"13457.0","high":"15282.0","last":"13457.0","type":"SPOT","open":14540.0,"volume":"32.915","sell":"13426.0","buy":"13341.0","at":1610177491,"name":"ETH/WRX"},"xrpwrx":{"base_unit":"xrp","quote_unit":"wrx","low":"3.52","high":"4.11","last":"3.55","type":"SPOT","open":3.8,"volume":"44455.0","sell":"3.54","buy":"3.53","at":1610177491,"name":"XRP/WRX"},"yfiwrx":{"base_unit":"yfi","quote_unit":"wrx","low":"399418.0","high":"460000.0","last":"412508.0","type":"SPOT","open":377651.0,"volume":"0.523585","sell":"450000.0","buy":"413555.0","at":1610177491,"name":"YFI/WRX"},"bnbwrx":{"base_unit":"bnb","quote_unit":"wrx","low":"467.0","high":"525.0","last":"474.0","type":"SPOT","open":516.0,"volume":"19.76","sell":"473.0","buy":"468.0","at":1610177491,"name":"BNB/WRX"},"trxwrx":{"base_unit":"trx","quote_unit":"wrx","low":"0.3476","high":"0.3769","last":"0.3476","type":"SPOT","open":0.3737,"volume":"56969.0","sell":"0.3463","buy":"0.3407","at":1610177491,"name":"TRX/WRX"},"eoswrx":{"base_unit":"eos","quote_unit":"wrx","low":"35.02","high":"450.0","last":"35.02","type":"SPOT","open":"35.02","volume":"2691.18","sell":"34.79","buy":"34.25","at":1610177491,"name":"EOS/WRX"}}