{"btcinr":{"base_unit":"btc","quote_unit":"inr","low":"2466054.0","high":"2660634.0","last":"2518301.0","type":"SPOT","open":2630000.0,"volume":"249.2549","sell":"2518957.0","buy":"2515191.0","at":1611679415,"name":"BTC/INR"},"xrpinr":{"base_unit":"xrp","quote_unit":"inr","low":"20.5","high":"21.639","last":"20.9","type":"SPOT","open":21.582,"volume":"1099902.0","sell":"20.9","buy":"20.8818","at":1611679415,"name":"XRP/INR"},"ethinr":{"base_unit":"eth","quote_unit":"inr","low":"99500.0","high":"110009.4","last":"102525.2","type":"SPOT","open":109401.0,"volume":"2637.701","sell":"102525.2","buy":"102410.2","at":1611679415,"name":"ETH/INR"},"trxinr":{"base_unit":"trx","quote_unit":"inr","low":"2.27","high":"2.4002","last":"2.3044","type":"SPOT","open":2.3999,"volume":"25375669.0","sell":"2.3047","buy":"2.3044","at":1611679415,"name":"TRX/INR"},"eosinr":{"base_unit":"eos","quote_unit":"inr","low":"205.0","high":"213.0","last":"205.5","type":"SPOT","open":212.5,"volume":"27858.19","sell":"207.29","buy":"205.5","at":1611679415,"name":"EOS/INR"},"zilinr":{"base_unit":"zil","quote_unit":"inr","low":"5.11","high":"5.36","last":"5.36","type":"SPOT","open":5.33,"volume":"4597.0","sell":"5.37","buy":"5.15","at":1611679415,"name":"ZIL/INR"},"batinr":{"base_unit":"bat","quote_unit":"inr","low":"22.25","high":"24.63","last":"22.989","type":"SPOT","open":24.72,"volume":"355626.83","sell":"22.988","buy":"22.7","at":1611679415,"name":"BAT/INR"},"usdtinr":{"base_unit":"usdt","quote_unit":"inr","low":"77.8","high":"79.49","last":"78.98","type":"SPOT","open":78.19,"volume":"7166959.0","sell":"78.97","buy":"78.89","at":1611679415,"name":"USDT/INR"},"wrxinr":{"base_unit":"wrx","quote_unit":"inr","low":"7.14","high":"7.5","last":"7.26","type":"SPOT","open":7.27,"volume":"2067610.0","sell":"7.26","buy":"7.2","at":1611679415,"name":"WRX/INR"},"maticinr":{"base_unit":"matic","quote_unit":"inr","low":"2.5","high":"3.35","last":"3.124","type":"SPOT","open":2.789,"volume":"13838028.0","sell":"3.125","buy":"3.118","at":1611679415,"name":"MATIC/INR"},"bchinr":{"base_unit":"bch","quote_unit":"inr","low":"32901.0","high":"35498.0","last":"33990.0","type":"SPOT","open":35402.0,"volume":"197.395","sell":"33989.0","buy":"33601.0","at":1611679415,"name":"BCH/INR"},"bnbinr":{"base_unit":"bnb","quote_unit":"inr","low":"3168.01","high":"3330.0","last":"3239.89","type":"SPOT","open":3313.07,"volume":"985.17","sell":"3239.89","buy":"3207.01","at":1611679415,"name":"BNB/INR"},"bttinr":{"base_unit":"btt","quote_unit":"inr","low":"0.02811","high":"0.02921","last":"0.02845","type":"SPOT","open":0.02898,"volume":"48308717.0","sell":"0.02847","buy":"0.02843","at":1611679415,"name":"BTT/INR"},"chzinr":{"base_unit":"chz","quote_unit":"inr","low":"2.5","high":"2.5","last":"2.5","type":"SPOT","open":2.5,"volume":"0.0","sell":"2.49","buy":"0.99132","at":1611679415,"name":"CHZ/INR"},"oneinr":{"base_unit":"one","quote_unit":"inr","low":"0.56","high":"0.56","last":"0.56","type":"SPOT","open":0.56,"volume":"0.0","sell":"0.56","buy":"0.35","at":1611679415,"name":"ONE/INR"},"yfiinr":{"base_unit":"yfi","quote_unit":"inr","low":"2275001.0","high":"2489275.0","last":"2320000.0","type":"SPOT","open":2450438.0,"volume":"9.424672","sell":"2324499.0","buy":"2320000.0","at":1611679415,"name":"YFI/INR"},"uniinr":{"base_unit":"uni","quote_unit":"inr","low":"860.0","high":"1045.0","last":"1044.89","type":"SPOT","open":890.0,"volume":"56270.98","sell":"1044.89","buy":"1040.0","at":1611679415,"name":"UNI/INR"},"linkinr":{"base_unit":"link","quote_unit":"inr","low":"1720.0","high":"1890.0","last":"1783.0","type":"SPOT","open":1871.0,"volume":"9074.85","sell":"1783.0","buy":"1760.0","at":1611679415,"name":"LINK/INR"},"sxpinr":{"base_unit":"sxp","quote_unit":"inr","low":"75.0","high":"82.5","last":"77.25","type":"SPOT","open":81.19,"volume":"96333.94","sell":"78.0","buy":"77.25","at":1611679415,"name":"SXP/INR"},"adainr":{"base_unit":"ada","quote_unit":"inr","low":"26.0","high":"27.8999","last":"26.75","type":"SPOT","open":27.6075,"volume":"462043.5","sell":"26.75","buy":"26.6014","at":1611679415,"name":"ADA/INR"},"nanoinr":{"base_unit":"nano","quote_unit":"inr","low":"380.0","high":"380.0","last":"380.0","type":"SPOT","open":380.0,"volume":"0.0","sell":"380.0","buy":"68.0","at":1611679415,"name":"NANO/INR"},"atominr":{"base_unit":"atom","quote_unit":"inr","low":"590.0","high":"644.0","last":"600.0","type":"SPOT","open":638.56,"volume":"18961.23","sell":"600.0","buy":"598.11","at":1611679415,"name":"ATOM/INR"},"xlminr":{"base_unit":"xlm","quote_unit":"inr","low":"19.5","high":"21.2977","last":"20.05","type":"SPOT","open":21.1226,"volume":"443932.1","sell":"20.29","buy":"20.05","at":1611679415,"name":"XLM/INR"},"fetinr":{"base_unit":"fet","quote_unit":"inr","low":"7.0","high":"7.0","last":"7.0","type":"SPOT","open":7.0,"volume":"0.0","sell":"9.0","buy":"3.0","at":1611679415,"name":"FET/INR"},"xeminr":{"base_unit":"xem","quote_unit":"inr","low":"17.149","high":"19.0","last":"18.12","type":"SPOT","open":17.342,"volume":"545421.0","sell":"18.15","buy":"18.12","at":1611679415,"name":"XEM/INR"},"zecinr":{"base_unit":"zec","quote_unit":"inr","low":"6700.0","high":"7311.4","last":"6776.59","type":"SPOT","open":7307.7,"volume":"547.866","sell":"6820.0","buy":"6711.01","at":1611679415,"name":"ZEC/INR"},"busdinr":{"base_unit":"busd","quote_unit":"inr","low":"77.6","high":"79.5","last":"79.5","type":"SPOT","open":77.65,"volume":"21187.99","sell":"79.49","buy":"78.14","at":1611679415,"name":"BUSD/INR"},"yfiiinr":{"base_unit":"yfii","quote_unit":"inr","low":"136000.0","high":"149000.0","last":"138598.0","type":"SPOT","open":147604.97,"volume":"168.739408","sell":"138597.0","buy":"137100.0","at":1611679415,"name":"YFII/INR"},"dogeinr":{"base_unit":"doge","quote_unit":"inr","low":"0.6388","high":"0.6732","last":"0.6487","type":"SPOT","open":0.673,"volume":"7746850.0","sell":"0.6487","buy":"0.6429","at":1611679415,"name":"DOGE/INR"},"dotinr":{"base_unit":"dot","quote_unit":"inr","low":"1280.0","high":"1400.0","last":"1323.86","type":"SPOT","open":1390.04,"volume":"25705.97","sell":"1323.86","buy":"1315.0","at":1611679415,"name":"DOT/INR"},"vetinr":{"base_unit":"vet","quote_unit":"inr","low":"2.259","high":"2.45007","last":"2.28045","type":"SPOT","open":2.42,"volume":"5433959.0","sell":"2.28498","buy":"2.28","at":1611679415,"name":"VET/INR"},"easyinr":{"base_unit":"easy","quote_unit":"inr","low":"0.0","high":"0.0","last":"0.0","type":"SPOT","open":"0.0","volume":"0.0","sell":"0.0","buy":"100.0","at":1611679415,"name":"EASY/INR"},"ltcinr":{"base_unit":"ltc","quote_unit":"inr","low":"10300.0","high":"11200.0","last":"10547.71","type":"SPOT","open":11105.5,"volume":"2355.987","sell":"10547.72","buy":"10501.05","at":1611679415,"name":"LTC/INR"},"dashinr":{"base_unit":"dash","quote_unit":"inr","low":"8001.0","high":"8678.0","last":"8189.0","type":"SPOT","open":8678.0,"volume":"397.215","sell":"8196.0","buy":"8100.0","at":1611679415,"name":"DASH/INR"},"xrpbtc":{"base_unit":"xrp","quote_unit":"btc","low":"0.00000804","high":"0.00000842","last":"0.00000835","type":"SPOT","open":8.17e-06,"volume":"199740.0","sell":"0.00000835","buy":"0.00000827","at":1611679415,"name":"XRP/BTC"},"trxbtc":{"base_unit":"trx","quote_unit":"btc","low":"0.0000009","high":"0.00000094","last":"0.00000093","type":"SPOT","open":9.2e-07,"volume":"209276.0","sell":"0.00000092","buy":"0.00000091","at":1611679415,"name":"TRX/BTC"},"ethbtc":{"base_unit":"eth","quote_unit":"btc","low":"0.040361","high":"0.042315","last":"0.040651","type":"SPOT","open":0.0414,"volume":"83.202","sell":"0.041007","buy":"0.040692","at":1611679415,"name":"ETH/BTC"},"ncashbtc":{"base_unit":"ncash","quote_unit":"btc","low":"0.00000002","high":"0.00000004","last":"0.00000003","type":"SPOT","open":3.0e-08,"volume":"737321.0","sell":"0.00000004","buy":"0.00000002","at":1611679415,"name":"NCASH/BTC"},"zilbtc":{"base_unit":"zil","quote_unit":"btc","low":"0.00000203","high":"0.00000213","last":"0.00000211","type":"SPOT","open":2.06e-06,"volume":"55942.0","sell":"0.00000212","buy":"0.00000207","at":1611679415,"name":"ZIL/BTC"},"batbtc":{"base_unit":"bat","quote_unit":"btc","low":"0.00000902","high":"0.0000095","last":"0.00000909","type":"SPOT","open":9.17e-06,"volume":"10455.43","sell":"0.00000925","buy":"0.00000909","at":1611679415,"name":"BAT/BTC"},"ltcbtc":{"base_unit":"ltc","quote_unit":"btc","low":"0.004185","high":"0.0043","last":"0.004185","type":"SPOT","open":0.004212,"volume":"15.148","sell":"0.004185","buy":"0.00418","at":1611679415,"name":"LTC/BTC"},"qkcbtc":{"base_unit":"qkc","quote_unit":"btc","low":"0.00000019","high":"0.00000021","last":"0.0000002","type":"SPOT","open":2.0e-07,"volume":"43014.0","sell":"0.00000021","buy":"0.0000002","at":1611679415,"name":"QKC/BTC"},"npxsbtc":{"base_unit":"npxs","quote_unit":"btc","low":"0.00000001","high":"0.00000002","last":"0.00000002","type":"SPOT","open":1.0e-08,"volume":"2756859.0","sell":"0.00000002","buy":"0.00000001","at":1611679415,"name":"NPXS/BTC"},"dashbtc":{"base_unit":"dash","quote_unit":"btc","low":"0.003225","high":"0.003275","last":"0.003275","type":"SPOT","open":0.003333,"volume":"12.762","sell":"0.003286","buy":"0.003226","at":1611679415,"name":"DASH/BTC"},"funbtc":{"base_unit":"fun","quote_unit":"btc","low":"0.00000052","high":"0.0000006","last":"0.00000059","type":"SPOT","open":5.5e-07,"volume":"3761.0","sell":"0.00000058","buy":"0.00000056","at":1611679415,"name":"FUN/BTC"},"iostbtc":{"base_unit":"iost","quote_unit":"btc","low":"0.00000047","high":"0.00000053","last":"0.00000052","type":"SPOT","open":5.0e-07,"volume":"114455.0","sell":"0.00000053","buy":"0.0000005","at":1611679415,"name":"IOST/BTC"},"nulsbtc":{"base_unit":"nuls","quote_unit":"btc","low":"0.00000949","high":"0.00001046","last":"0.00000972","type":"SPOT","open":1.035e-05,"volume":"3216.0","sell":"0.00000976","buy":"0.00000948","at":1611679415,"name":"NULS/BTC"},"omgbtc":{"base_unit":"omg","quote_unit":"btc","low":"0.000107","high":"0.000113","last":"0.000107","type":"SPOT","open":0.000113,"volume":"127.82","sell":"0.000107","buy":"0.000103","at":1611679415,"name":"OMG/BTC"},"poebtc":{"base_unit":"poe","quote_unit":"btc","low":"0.00000005","high":"0.00000005","last":"0.00000005","type":"SPOT","open":5.0e-08,"volume":"0.0","sell":"0.00000006","buy":"0.00000002","at":1611679415,"name":"POE/BTC"},"reqbtc":{"base_unit":"req","quote_unit":"btc","low":"0.00000105","high":"0.00000118","last":"0.00000114","type":"SPOT","open":1.05e-06,"volume":"3712.0","sell":"0.00000116","buy":"0.00000112","at":1611679415,"name":"REQ/BTC"},"sntbtc":{"base_unit":"snt","quote_unit":"btc","low":"0.00000144","high":"0.00000144","last":"0.00000144","type":"SPOT","open":1.44e-06,"volume":"7300.0","sell":"0.00000146","buy":"0.00000142","at":1611679415,"name":"SNT/BTC"},"thetabtc":{"base_unit":"theta","quote_unit":"btc","low":"0.00006481","high":"0.00007488","last":"0.00007062","type":"SPOT","open":6.232e-05,"volume":"1180.0","sell":"0.00007144","buy":"0.00007065","at":1611679415,"name":"THETA/BTC"},"zrxbtc":{"base_unit":"zrx","quote_unit":"btc","low":"0.0000161","high":"0.00001697","last":"0.00001655","type":"SPOT","open":1.61e-05,"volume":"98.46","sell":"0.00001629","buy":"0.00001568","at":1611679415,"name":"ZRX/BTC"},"eosbtc":{"base_unit":"eos","quote_unit":"btc","low":"0.00008","high":"0.000083","last":"0.0000815","type":"SPOT","open":8.0e-05,"volume":"143.59","sell":"0.0000822","buy":"0.0000816","at":1611679415,"name":"EOS/BTC"},"icxbtc":{"base_unit":"icx","quote_unit":"btc","low":"0.0000253","high":"0.0000286","last":"0.0000268","type":"SPOT","open":2.49e-05,"volume":"3094.2","sell":"0.0000269","buy":"0.0000262","at":1611679415,"name":"ICX/BTC"},"hotbtc":{"base_unit":"hot","quote_unit":"btc","low":"0.00000002","high":"0.00000003","last":"0.00000003","type":"SPOT","open":3.0e-08,"volume":"424384.0","sell":"0.00000003","buy":"0.00000002","at":1611679415,"name":"HOT/BTC"},"polybtc":{"base_unit":"poly","quote_unit":"btc","low":"0.00000289","high":"0.00000305","last":"0.00000295","type":"SPOT","open":2.95e-06,"volume":"3775.0","sell":"0.00000298","buy":"0.00000286","at":1611679415,"name":"POLY/BTC"},"paxbtc":{"base_unit":"pax","quote_unit":"btc","low":"0.0","high":"0.0","last":"0.0","type":"SPOT","open":"0.0","volume":"0.0","sell":"0.0","buy":"0.00000001","at":1611679415,"name":"PAX/BTC"},"usdcbtc":{"base_unit":"usdc","quote_unit":"btc","low":"0.0","high":"0.0","last":"0.0","type":"SPOT","open":"0.0","volume":"0.0","sell":"0.0","buy":"0.0","at":1611679415,"name":"USDC/BTC"},"xlmbtc":{"base_unit":"xlm","quote_unit":"btc","low":"0.0","high":"0.0","last":"0.0","type":"SPOT","open":"0.0","volume":"0.0","sell":"0.0","buy":"0.0","at":1611679415,"name":"XLM/BTC"},"bttbtc":{"base_unit":"btt","quote_unit":"btc","low":"0.00000001","high":"0.00000002","last":"0.00000001","type":"SPOT","open":1.0e-08,"volume":"2782412.0","sell":"0.00000002","buy":"0.00000001","at":1611679415,"name":"BTT/BTC"},"fetbtc":{"base_unit":"fet","quote_unit":"btc","low":"0.00000252","high":"0.00000269","last":"0.00000263","type":"SPOT","open":2.54e-06,"volume":"9669.0","sell":"0.00000272","buy":"0.00000263","at":1611679415,"name":"FET/BTC"},"celrbtc":{"base_unit":"celr","quote_unit":"btc","low":"0.00000021","high":"0.00000023","last":"0.00000021","type":"SPOT","open":2.2e-07,"volume":"60197.0","sell":"0.00000022","buy":"0.00000021","at":1611679415,"name":"CELR/BTC"},"maticbtc":{"base_unit":"matic","quote_unit":"btc","low":"0.00000102","high":"0.0000013","last":"0.00000122","type":"SPOT","open":1.04e-06,"volume":"198401.0","sell":"0.00000125","buy":"0.00000122","at":1611679415,"name":"MATIC/BTC"},"adabtc":{"base_unit":"ada","quote_unit":"btc","low":"0.0000105","high":"0.00001082","last":"0.00001059","type":"SPOT","open":1.049e-05,"volume":"8286.2","sell":"0.00001072","buy":"0.00001059","at":1611679415,"name":"ADA/BTC"},"rvnbtc":{"base_unit":"rvn","quote_unit":"btc","low":"0.00000048","high":"0.00000052","last":"0.0000005","type":"SPOT","open":4.9e-07,"volume":"13792.0","sell":"0.00000052","buy":"0.00000051","at":1611679415,"name":"RVN/BTC"},"xmrbtc":{"base_unit":"xmr","quote_unit":"btc","low":"0.004222","high":"0.004366","last":"0.00435","type":"SPOT","open":0.00429,"volume":"9.477","sell":"0.00435","buy":"0.004309","at":1611679415,"name":"XMR/BTC"},"atombtc":{"base_unit":"atom","quote_unit":"btc","low":"0.0002367","high":"0.0002469","last":"0.0002396","type":"SPOT","open":0.0002424,"volume":"190.52","sell":"0.0002397","buy":"0.0002395","at":1611679415,"name":"ATOM/BTC"},"bnbbtc":{"base_unit":"bnb","quote_unit":"btc","low":"0.0012512","high":"0.0013045","last":"0.0012779","type":"SPOT","open":0.0012591,"volume":"389.68","sell":"0.0012831","buy":"0.001276","at":1611679415,"name":"BNB/BTC"},"wrxbtc":{"base_unit":"wrx","quote_unit":"btc","low":"0.00000271","high":"0.00000293","last":"0.0000029","type":"SPOT","open":2.74e-06,"volume":"71797.0","sell":"0.0000029","buy":"0.00000284","at":1611679415,"name":"WRX/BTC"},"fttbtc":{"base_unit":"ftt","quote_unit":"btc","low":"0.0003035","high":"0.0003076","last":"0.0003076","type":"SPOT","open":0.0003097,"volume":"4.101","sell":"0.0003063","buy":"0.0003029","at":1611679415,"name":"FTT/BTC"},"stmxbtc":{"base_unit":"stmx","quote_unit":"btc","low":"0.00000008","high":"0.00000009","last":"0.00000009","type":"SPOT","open":8.0e-08,"volume":"55290.0","sell":"0.00000009","buy":"0.00000008","at":1611679415,"name":"STMX/BTC"},"glmbtc":{"base_unit":"glm","quote_unit":"btc","low":"0.0","high":"0.0","last":"0.0","type":"SPOT","open":"0.0","volume":"0.0","sell":"0.0","buy":"0.0","at":1611679415,"name":"GLM/BTC"},"btcusdt":{"base_unit":"btc","quote_unit":"usdt","low":"31000.0","high":"34100.0","last":"31845.0","type":"SPOT","open":33814.0,"volume":"28.603","sell":"31874.0","buy":"31853.0","at":1611679415,"name":"BTC/USDT"},"trxusdt":{"base_unit":"trx","quote_unit":"usdt","low":"0.02853","high":"0.03067","last":"0.02901","type":"SPOT","open":0.03056,"volume":"7166608.0","sell":"0.02921","buy":"0.02903","at":1611679415,"name":"TRX/USDT"},"xrpusdt":{"base_unit":"xrp","quote_unit":"usdt","low":"0.25794","high":"0.27585","last":"0.26407","type":"SPOT","open":0.27518,"volume":"595220.0","sell":"0.26461","buy":"0.26407","at":1611679415,"name":"XRP/USDT"},"eosusdt":{"base_unit":"eos","quote_unit":"usdt","low":"2.5641","high":"2.7089","last":"2.5903","type":"SPOT","open":2.7167,"volume":"23769.89","sell":"2.6124","buy":"2.5924","at":1611679415,"name":"EOS/USDT"},"ethusdt":{"base_unit":"eth","quote_unit":"usdt","low":"1250.0","high":"1414.83","last":"1304.96","type":"SPOT","open":1400.0,"volume":"1137.085","sell":"1309.79","buy":"1304.28","at":1611679415,"name":"ETH/USDT"},"icxusdt":{"base_unit":"icx","quote_unit":"usdt","low":"0.8067","high":"0.95","last":"0.8481","type":"SPOT","open":0.8609,"volume":"50906.58","sell":"0.8568","buy":"0.8491","at":1611679415,"name":"ICX/USDT"},"ltcusdt":{"base_unit":"ltc","quote_unit":"usdt","low":"129.0","high":"143.68","last":"133.0","type":"SPOT","open":142.05,"volume":"1595.01","sell":"134.0","buy":"133.3","at":1611679415,"name":"LTC/USDT"},"tusdusdt":{"base_unit":"tusd","quote_unit":"usdt","low":"0.9955","high":"1.004","last":"0.9955","type":"SPOT","open":1.003,"volume":"844.7","sell":"1.0036","buy":"0.9951","at":1611679415,"name":"TUSD/USDT"},"npxsusdt":{"base_unit":"npxs","quote_unit":"usdt","low":"0.000426","high":"0.000484","last":"0.000442","type":"SPOT","open":0.000446,"volume":"96514292.0","sell":"0.000442","buy":"0.000436","at":1611679415,"name":"NPXS/USDT"},"hotusdt":{"base_unit":"hot","quote_unit":"usdt","low":"0.0006463","high":"0.0006825","last":"0.0006522","type":"SPOT","open":0.0006796,"volume":"4893719.0","sell":"0.0006569","buy":"0.0006503","at":1611679415,"name":"HOT/USDT"},"batusdt":{"base_unit":"bat","quote_unit":"usdt","low":"0.281","high":"0.314","last":"0.2854","type":"SPOT","open":0.3108,"volume":"304633.2","sell":"0.2933","buy":"0.2914","at":1611679415,"name":"BAT/USDT"},"dashusdt":{"base_unit":"dash","quote_unit":"usdt","low":"100.65","high":"109.89","last":"103.89","type":"SPOT","open":109.89,"volume":"506.658","sell":"104.0","buy":"103.42","at":1611679415,"name":"DASH/USDT"},"ncashusdt":{"base_unit":"ncash","quote_unit":"usdt","low":"0.000912","high":"0.000999","last":"0.000957","type":"SPOT","open":0.000999,"volume":"5057184.0","sell":"0.000958","buy":"0.000957","at":1611679415,"name":"NCASH/USDT"},"qkcusdt":{"base_unit":"qkc","quote_unit":"usdt","low":"0.00622","high":"0.00696","last":"0.00658","type":"SPOT","open":0.00691,"volume":"718250.0","sell":"0.0065","buy":"0.00635","at":1611679415,"name":"QKC/USDT"},"zilusdt":{"base_unit":"zil","quote_unit":"usdt","low":"0.06403","high":"0.06939","last":"0.0666","type":"SPOT","open":0.06976,"volume":"855035.0","sell":"0.06705","buy":"0.0666","at":1611679415,"name":"ZIL/USDT"},"zrxusdt":{"base_unit":"zrx","quote_unit":"usdt","low":"0.4991","high":"0.5374","last":"0.4991","type":"SPOT","open":0.5466,"volume":"8298.89","sell":"0.5126","buy":"0.511","at":1611679415,"name":"ZRX/USDT"},"bchusdt":{"base_unit":"bch","quote_unit":"usdt","low":"417.37","high":"454.0","last":"426.59","type":"SPOT","open":450.97,"volume":"142.239","sell":"426.97","buy":"423.87","at":1611679415,"name":"BCH/USDT"},"bchsvusdt":{"base_unit":"bchsv","quote_unit":"usdt","low":"171.0","high":"181.98","last":"173.24","type":"SPOT","open":182.48,"volume":"17.305","sell":"177.97","buy":"173.24","at":1611679415,"name":"BCHSV/USDT"},"paxusdt":{"base_unit":"pax","quote_unit":"usdt","low":"0.9953","high":"0.999","last":"0.9953","type":"SPOT","open":0.999,"volume":"637.25","sell":"0.9953","buy":"0.9951","at":1611679415,"name":"PAX/USDT"},"usdcusdt":{"base_unit":"usdc","quote_unit":"usdt","low":"0.997","high":"1.002","last":"0.999","type":"SPOT","open":0.996,"volume":"18791.32","sell":"0.999","buy":"0.998","at":1611679415,"name":"USDC/USDT"},"omgusdt":{"base_unit":"omg","quote_unit":"usdt","low":"3.3127","high":"3.8099","last":"3.3548","type":"SPOT","open":3.69,"volume":"2753.63","sell":"3.4088","buy":"3.3786","at":1611679415,"name":"OMG/USDT"},"polyusdt":{"base_unit":"poly","quote_unit":"usdt","low":"0.091","high":"0.1001","last":"0.0928","type":"SPOT","open":0.1,"volume":"19036.0","sell":"0.0939","buy":"0.0919","at":1611679415,"name":"POLY/USDT"},"dentusdt":{"base_unit":"dent","quote_unit":"usdt","low":"0.000274","high":"0.0003","last":"0.000276","type":"SPOT","open":0.000296,"volume":"26378378.0","sell":"0.00028","buy":"0.000277","at":1611679415,"name":"DENT/USDT"},"iostusdt":{"base_unit":"iost","quote_unit":"usdt","low":"0.01515","high":"0.01742","last":"0.01657","type":"SPOT","open":0.01715,"volume":"2069960.0","sell":"0.01665","buy":"0.01651","at":1611679415,"name":"IOST/USDT"},"funusdt":{"base_unit":"fun","quote_unit":"usdt","low":"0.017661","high":"0.019296","last":"0.017661","type":"SPOT","open":0.018549,"volume":"866491.0","sell":"0.018176","buy":"0.017828","at":1611679415,"name":"FUN/USDT"},"poeusdt":{"base_unit":"poe","quote_unit":"usdt","low":"0.000709","high":"0.000709","last":"0.000709","type":"SPOT","open":0.000709,"volume":"0.0","sell":"0.000828","buy":"0.000504","at":1611679415,"name":"POE/USDT"},"sntusdt":{"base_unit":"snt","quote_unit":"usdt","low":"0.04388","high":"0.04952","last":"0.045","type":"SPOT","open":0.04978,"volume":"69924.0","sell":"0.04603","buy":"0.045","at":1611679415,"name":"SNT/USDT"},"thetausdt":{"base_unit":"theta","quote_unit":"usdt","low":"2.08915","high":"2.40489","last":"2.27385","type":"SPOT","open":2.17257,"volume":"25085.0","sell":"2.28419","buy":"2.27385","at":1611679415,"name":"THETA/USDT"},"requsdt":{"base_unit":"req","quote_unit":"usdt","low":"0.03505","high":"0.03771","last":"0.03609","type":"SPOT","open":0.0366,"volume":"34102.0","sell":"0.03659","buy":"0.03547","at":1611679415,"name":"REQ/USDT"},"xlmusdt":{"base_unit":"xlm","quote_unit":"usdt","low":"0.24827","high":"0.27145","last":"0.25718","type":"SPOT","open":0.27111,"volume":"379208.7","sell":"0.25767","buy":"0.25573","at":1611679415,"name":"XLM/USDT"},"xtzusdt":{"base_unit":"xtz","quote_unit":"usdt","low":"2.7931","high":"3.0787","last":"2.7931","type":"SPOT","open":3.0315,"volume":"3341.58","sell":"2.8975","buy":"2.8755","at":1611679415,"name":"XTZ/USDT"},"bttusdt":{"base_unit":"btt","quote_unit":"usdt","low":"0.0003514","high":"0.0003741","last":"0.0003569","type":"SPOT","open":0.0003723,"volume":"27970033.0","sell":"0.00036","buy":"0.0003533","at":1611679416,"name":"BTT/USDT"},"fetusdt":{"base_unit":"fet","quote_unit":"usdt","low":"0.08","high":"0.0866","last":"0.0843","type":"SPOT","open":0.0849,"volume":"236279.0","sell":"0.086","buy":"0.0853","at":1611679416,"name":"FET/USDT"},"tfuelusdt":{"base_unit":"tfuel","quote_unit":"usdt","low":"0.02937","high":"0.0346","last":"0.0321","type":"SPOT","open":0.03001,"volume":"1087925.0","sell":"0.03262","buy":"0.03228","at":1611679416,"name":"TFUEL/USDT"},"celrusdt":{"base_unit":"celr","quote_unit":"usdt","low":"0.00654","high":"0.00734","last":"0.00677","type":"SPOT","open":0.00741,"volume":"1819430.0","sell":"0.00697","buy":"0.00686","at":1611679416,"name":"CELR/USDT"},"maticusdt":{"base_unit":"matic","quote_unit":"usdt","low":"0.032","high":"0.0421","last":"0.03971","type":"SPOT","open":0.03503,"volume":"8511964.1","sell":"0.03999","buy":"0.03903","at":1611679416,"name":"MATIC/USDT"},"adausdt":{"base_unit":"ada","quote_unit":"usdt","low":"0.32716","high":"0.35625","last":"0.34072","type":"SPOT","open":0.35571,"volume":"428760.7","sell":"0.34078","buy":"0.33896","at":1611679416,"name":"ADA/USDT"},"rvnusdt":{"base_unit":"rvn","quote_unit":"usdt","low":"0.01591","high":"0.01739","last":"0.01625","type":"SPOT","open":0.01714,"volume":"131618.0","sell":"0.01625","buy":"0.01615","at":1611679416,"name":"RVN/USDT"},"xmrusdt":{"base_unit":"xmr","quote_unit":"usdt","low":"133.24","high":"144.01","last":"138.11","type":"SPOT","open":142.68,"volume":"34.723","sell":"138.8","buy":"137.76","at":1611679416,"name":"XMR/USDT"},"atomusdt":{"base_unit":"atom","quote_unit":"usdt","low":"7.432","high":"8.26","last":"7.6","type":"SPOT","open":8.188,"volume":"12501.72","sell":"7.651","buy":"7.582","at":1611679416,"name":"ATOM/USDT"},"algousdt":{"base_unit":"algo","quote_unit":"usdt","low":"0.54","high":"0.602","last":"0.563","type":"SPOT","open":0.602,"volume":"63244.81","sell":"0.565","buy":"0.559","at":1611679416,"name":"ALGO/USDT"},"linkusdt":{"base_unit":"link","quote_unit":"usdt","low":"21.7897","high":"24.3343","last":"22.4636","type":"SPOT","open":23.75,"volume":"6789.73","sell":"22.5581","buy":"22.3922","at":1611679416,"name":"LINK/USDT"},"qtumusdt":{"base_unit":"qtum","quote_unit":"usdt","low":"3.222","high":"3.516","last":"3.247","type":"SPOT","open":3.427,"volume":"2367.416","sell":"3.342","buy":"3.315","at":1611679416,"name":"QTUM/USDT"},"etcusdt":{"base_unit":"etc","quote_unit":"usdt","low":"7.1919","high":"7.7495","last":"7.2541","type":"SPOT","open":7.6928,"volume":"229.68","sell":"7.3248","buy":"7.2614","at":1611679416,"name":"ETC/USDT"},"iotausdt":{"base_unit":"iota","quote_unit":"usdt","low":"0.4105","high":"0.464","last":"0.4185","type":"SPOT","open":0.457,"volume":"12334.11","sell":"0.4282","buy":"0.4237","at":1611679416,"name":"IOTA/USDT"},"zecusdt":{"base_unit":"zec","quote_unit":"usdt","low":"84.15","high":"92.49","last":"85.63","type":"SPOT","open":91.53,"volume":"545.046","sell":"85.93","buy":"85.33","at":1611679416,"name":"ZEC/USDT"},"wavesusdt":{"base_unit":"waves","quote_unit":"usdt","low":"6.5","high":"7.0666","last":"6.555","type":"SPOT","open":7.1852,"volume":"1213.66","sell":"6.6549","buy":"6.5841","at":1611679416,"name":"WAVES/USDT"},"ftmusdt":{"base_unit":"ftm","quote_unit":"usdt","low":"0.05085","high":"0.0664","last":"0.0645","type":"SPOT","open":0.0531,"volume":"807479.8","sell":"0.06567","buy":"0.0646","at":1611679416,"name":"FTM/USDT"},"enjusdt":{"base_unit":"enj","quote_unit":"usdt","low":"0.38559","high":"0.486","last":"0.40457","type":"SPOT","open":0.41204,"volume":"96453.5","sell":"0.42","buy":"0.41536","at":1611679416,"name":"ENJ/USDT"},"lskusdt":{"base_unit":"lsk","quote_unit":"usdt","low":"1.27","high":"1.3859","last":"1.27","type":"SPOT","open":1.3859,"volume":"1449.14","sell":"1.2951","buy":"1.2766","at":1611679416,"name":"LSK/USDT"},"steemusdt":{"base_unit":"steem","quote_unit":"usdt","low":"0.1752","high":"0.186","last":"0.1779","type":"SPOT","open":0.1859,"volume":"6316.88","sell":"0.1807","buy":"0.176","at":1611679416,"name":"STEEM/USDT"},"xvgusdt":{"base_unit":"xvg","quote_unit":"usdt","low":"0.01089","high":"0.01224","last":"0.01119","type":"SPOT","open":0.01222,"volume":"839263.0","sell":"0.01119","buy":"0.01082","at":1611679416,"name":"XVG/USDT"},"loomusdt":{"base_unit":"loom","quote_unit":"usdt","low":"0.06337","high":"0.07225","last":"0.0646","type":"SPOT","open":0.06424,"volume":"94112.0","sell":"0.06639","buy":"0.06527","at":1611679416,"name":"LOOM/USDT"},"manausdt":{"base_unit":"mana","quote_unit":"usdt","low":"0.14941","high":"0.16677","last":"0.15479","type":"SPOT","open":0.1672,"volume":"43059.0","sell":"0.15773","buy":"0.15546","at":1611679416,"name":"MANA/USDT"},"repusdt":{"base_unit":"rep","quote_unit":"usdt","low":"18.645","high":"20.105","last":"18.645","type":"SPOT","open":20.254,"volume":"49.278","sell":"18.733","buy":"18.523","at":1611679416,"name":"REP/USDT"},"blzusdt":{"base_unit":"blz","quote_unit":"usdt","low":"0.13388","high":"0.15802","last":"0.13895","type":"SPOT","open":0.14399,"volume":"149720.0","sell":"0.14307","buy":"0.14","at":1611679416,"name":"BLZ/USDT"},"xzcusdt":{"base_unit":"xzc","quote_unit":"usdt","low":"3.4","high":"4.399","last":"4.177","type":"SPOT","open":4.399,"volume":"1078.28","sell":"4.17","buy":"3.622","at":1611679416,"name":"XZC/USDT"},"nanousdt":{"base_unit":"nano","quote_unit":"usdt","low":"3.0497","high":"3.35","last":"3.1317","type":"SPOT","open":3.35,"volume":"3176.63","sell":"3.1841","buy":"3.1405","at":1611679416,"name":"NANO/USDT"},"scusdt":{"base_unit":"sc","quote_unit":"usdt","low":"0.0042","high":"0.00467","last":"0.00429","type":"SPOT","open":0.00464,"volume":"2514096.0","sell":"0.00433","buy":"0.00429","at":1611679416,"name":"SC/USDT"},"btgusdt":{"base_unit":"btg","quote_unit":"usdt","low":"10.3","high":"11.15","last":"10.67","type":"SPOT","open":11.2,"volume":"356.89","sell":"10.7","buy":"10.46","at":1611679416,"name":"BTG/USDT"},"xemusdt":{"base_unit":"xem","quote_unit":"usdt","low":"0.22","high":"0.2414","last":"0.2323","type":"SPOT","open":0.2221,"volume":"405112.0","sell":"0.2329","buy":"0.2292","at":1611679416,"name":"XEM/USDT"},"btsusdt":{"base_unit":"bts","quote_unit":"usdt","low":"0.02264","high":"0.02444","last":"0.02319","type":"SPOT","open":0.02421,"volume":"80830.0","sell":"0.02328","buy":"0.02283","at":1611679416,"name":"BTS/USDT"},"ardrusdt":{"base_unit":"ardr","quote_unit":"usdt","low":"0.07732","high":"0.08154","last":"0.07752","type":"SPOT","open":0.08175,"volume":"6697.0","sell":"0.07818","buy":"0.07708","at":1611679416,"name":"ARDR/USDT"},"nasusdt":{"base_unit":"nas","quote_unit":"usdt","low":"0.2792","high":"0.3135","last":"0.2871","type":"SPOT","open":0.3081,"volume":"6311.19","sell":"0.2884","buy":"0.2793","at":1611679416,"name":"NAS/USDT"},"winusdt":{"base_unit":"win","quote_unit":"usdt","low":"0.0000898","high":"0.0000964","last":"0.0000919","type":"SPOT","open":9.62e-05,"volume":"17647064.0","sell":"0.0000917","buy":"0.0000905","at":1611679416,"name":"WIN/USDT"},"bnbusdt":{"base_unit":"bnb","quote_unit":"usdt","low":"40.0","high":"42.5922","last":"40.899","type":"SPOT","open":42.3767,"volume":"1040.43","sell":"40.8978","buy":"40.6928","at":1611679416,"name":"BNB/USDT"},"chzusdt":{"base_unit":"chz","quote_unit":"usdt","low":"0.018786","high":"0.020508","last":"0.019758","type":"SPOT","open":0.020313,"volume":"94161.0","sell":"0.019948","buy":"0.019698","at":1611679416,"name":"CHZ/USDT"},"wrxusdt":{"base_unit":"wrx","quote_unit":"usdt","low":"0.08935","high":"0.09529","last":"0.091","type":"SPOT","open":0.09317,"volume":"1323532.0","sell":"0.09116","buy":"0.09074","at":1611679416,"name":"WRX/USDT"},"kavausdt":{"base_unit":"kava","quote_unit":"usdt","low":"2.1228","high":"2.4317","last":"2.1997","type":"SPOT","open":2.4109,"volume":"5518.5","sell":"2.2111","buy":"2.1903","at":1611679416,"name":"KAVA/USDT"},"ankrusdt":{"base_unit":"ankr","quote_unit":"usdt","low":"0.00985","high":"0.01127","last":"0.010211","type":"SPOT","open":0.011344,"volume":"1769139.0","sell":"0.010417","buy":"0.010228","at":1611679416,"name":"ANKR/USDT"},"busdusdt":{"base_unit":"busd","quote_unit":"usdt","low":"0.997","high":"0.9978","last":"0.997","type":"SPOT","open":0.9974,"volume":"12028.21","sell":"1.0018","buy":"0.9969","at":1611679416,"name":"BUSD/USDT"},"oneusdt":{"base_unit":"one","quote_unit":"usdt","low":"0.00685","high":"0.00743","last":"0.00691","type":"SPOT","open":0.00734,"volume":"543425.0","sell":"0.00706","buy":"0.00699","at":1611679416,"name":"ONE/USDT"},"ognusdt":{"base_unit":"ogn","quote_unit":"usdt","low":"0.0","high":"0.0","last":"0.0","type":"SPOT","open":"0.0","volume":"0.0","sell":"0.0","buy":"0.0","at":1611679416,"name":"OGN/USDT"},"hiveusdt":{"base_unit":"hive","quote_unit":"usdt","low":"0.1348","high":"0.1499","last":"0.1348","type":"SPOT","open":0.1503,"volume":"11625.05","sell":"0.1406","buy":"0.1348","at":1611679416,"name":"HIVE/USDT"},"fttusdt":{"base_unit":"ftt","quote_unit":"usdt","low":"9.625","high":"10.377","last":"9.625","type":"SPOT","open":10.377,"volume":"59.97","sell":"9.779","buy":"9.703","at":1611679416,"name":"FTT/USDT"},"bandusdt":{"base_unit":"band","quote_unit":"usdt","low":"8.3623","high":"9.834","last":"8.8234","type":"SPOT","open":9.8,"volume":"5815.21","sell":"8.8689","buy":"8.8061","at":1611679416,"name":"BAND/USDT"},"jstusdt":{"base_unit":"jst","quote_unit":"usdt","low":"0.02825","high":"0.03195","last":"0.02825","type":"SPOT","open":0.03135,"volume":"214761.0","sell":"0.02874","buy":"0.02832","at":1611679416,"name":"JST/USDT"},"ctsiusdt":{"base_unit":"ctsi","quote_unit":"usdt","low":"0.05396","high":"0.05971","last":"0.05505","type":"SPOT","open":0.05844,"volume":"34846.6","sell":"0.0564","buy":"0.05572","at":1611679416,"name":"CTSI/USDT"},"chrusdt":{"base_unit":"chr","quote_unit":"usdt","low":"0.02893","high":"0.03143","last":"0.02934","type":"SPOT","open":0.03113,"volume":"132811.0","sell":"0.0295","buy":"0.02914","at":1611679416,"name":"CHR/USDT"},"tomousdt":{"base_unit":"tomo","quote_unit":"usdt","low":"1.15","high":"1.292","last":"1.19","type":"SPOT","open":1.2768,"volume":"5665.53","sell":"1.2095","buy":"1.1954","at":1611679416,"name":"TOMO/USDT"},"stxusdt":{"base_unit":"stx","quote_unit":"usdt","low":"0.0","high":"0.0","last":"0.0","type":"SPOT","open":"0.0","volume":"0.0","sell":"0.0","buy":"0.0","at":1611679416,"name":"STX/USDT"},"stmxusdt":{"base_unit":"stmx","quote_unit":"usdt","low":"0.002604","high":"0.00283","last":"0.002666","type":"SPOT","open":0.00283,"volume":"963335.0","sell":"0.002666","buy":"0.002621","at":1611679416,"name":"STMX/USDT"},"gxsusdt":{"base_unit":"gxs","quote_unit":"usdt","low":"0.3419","high":"0.3614","last":"0.3419","type":"SPOT","open":0.3658,"volume":"3499.63","sell":"0.3569","buy":"0.3496","at":1611679416,"name":"GXS/USDT"},"mdtusdt":{"base_unit":"mdt","quote_unit":"usdt","low":"0.0","high":"0.0","last":"0.0","type":"SPOT","open":"0.0","volume":"0.0","sell":"0.0","buy":"0.0","at":1611679416,"name":"MDT/USDT"},"ltousdt":{"base_unit":"lto","quote_unit":"usdt","low":"0.0","high":"0.0","last":"0.0","type":"SPOT","open":"0.0","volume":"0.0","sell":"0.0","buy":"0.0","at":1611679416,"name":"LTO/USDT"},"lrcusdt":{"base_unit":"lrc","quote_unit":"usdt","low":"0.39465","high":"0.45015","last":"0.40912","type":"SPOT","open":0.44691,"volume":"18935.0","sell":"0.4167","buy":"0.41216","at":1611679416,"name":"LRC/USDT"},"dogeusdt":{"base_unit":"doge","quote_unit":"usdt","low":"0.0080102","high":"0.0086307","last":"0.0081464","type":"SPOT","open":0.0085854,"volume":"4873048.0","sell":"0.0082861","buy":"0.0082007","at":1611679416,"name":"DOGE/USDT"},"neousdt":{"base_unit":"neo","quote_unit":"usdt","low":"22.307","high":"24.454","last":"22.688","type":"SPOT","open":24.317,"volume":"1255.944","sell":"23.08","buy":"22.934","at":1611679416,"name":"NEO/USDT"},"hbarusdt":{"base_unit":"hbar","quote_unit":"usdt","low":"0.0","high":"0.0","last":"0.0","type":"SPOT","open":"0.0","volume":"0.0","sell":"0.0","buy":"0.0","at":1611679416,"name":"HBAR/USDT"},"storjusdt":{"base_unit":"storj","quote_unit":"usdt","low":"0.375","high":"0.41","last":"0.4009","type":"SPOT","open":0.3946,"volume":"23667.0","sell":"0.4041","buy":"0.4017","at":1611679416,"name":"STORJ/USDT"},"compusdt":{"base_unit":"comp","quote_unit":"usdt","low":"208.66","high":"231.68","last":"221.77","type":"SPOT","open":227.03,"volume":"104.133","sell":"223.86","buy":"221.35","at":1611679416,"name":"COMP/USDT"},"cotiusdt":{"base_unit":"coti","quote_unit":"usdt","low":"0.0631","high":"0.07289","last":"0.06512","type":"SPOT","open":0.07198,"volume":"122007.6","sell":"0.06628","buy":"0.06548","at":1611679416,"name":"COTI/USDT"},"dgbusdt":{"base_unit":"dgb","quote_unit":"usdt","low":"0.02358","high":"0.02559","last":"0.02379","type":"SPOT","open":0.0257,"volume":"323928.0","sell":"0.02424","buy":"0.0239","at":1611679416,"name":"DGB/USDT"},"grsusdt":{"base_unit":"grs","quote_unit":"usdt","low":"0.3458","high":"0.3667","last":"0.3541","type":"SPOT","open":0.3667,"volume":"1345.0","sell":"0.3623","buy":"0.3539","at":1611679416,"name":"GRS/USDT"},"snxusdt":{"base_unit":"snx","quote_unit":"usdt","low":"14.836","high":"16.42","last":"15.388","type":"SPOT","open":15.952,"volume":"1211.367","sell":"15.763","buy":"15.585","at":1611679416,"name":"SNX/USDT"},"renusdt":{"base_unit":"ren","quote_unit":"usdt","low":"0.53","high":"0.60621","last":"0.55018","type":"SPOT","open":0.60294,"volume":"22344.0","sell":"0.55838","buy":"0.55161","at":1611679416,"name":"REN/USDT"},"sxpusdt":{"base_unit":"sxp","quote_unit":"usdt","low":"0.952","high":"1.046","last":"0.968","type":"SPOT","open":1.045,"volume":"71857.63","sell":"0.993","buy":"0.976","at":1611679416,"name":"SXP/USDT"},"mkrusdt":{"base_unit":"mkr","quote_unit":"usdt","low":"1312.0","high":"1424.54","last":"1349.37","type":"SPOT","open":1421.59,"volume":"2.92482","sell":"1374.6","buy":"1359.87","at":1611679416,"name":"MKR/USDT"},"daiusdt":{"base_unit":"dai","quote_unit":"usdt","low":"0.0","high":"0.0","last":"0.0","type":"SPOT","open":"0.0","volume":"0.0","sell":"0.0","buy":"0.0","at":1611679416,"name":"DAI/USDT"},"avausdt":{"base_unit":"ava","quote_unit":"usdt","low":"1.6489","high":"1.8","last":"1.6489","type":"SPOT","open":1.7594,"volume":"2588.28","sell":"1.7232","buy":"1.6529","at":1611679416,"name":"AVA/USDT"},"balusdt":{"base_unit":"bal","quote_unit":"usdt","low":"0.0","high":"0.0","last":"0.0","type":"SPOT","open":"0.0","volume":"0.0","sell":"0.0","buy":"0.0","at":1611679416,"name":"BAL/USDT"},"srmusdt":{"base_unit":"srm","quote_unit":"usdt","low":"1.8654","high":"2.0552","last":"1.9878","type":"SPOT","open":2.0,"volume":"12434.56","sell":"1.9998","buy":"1.9797","at":1611679416,"name":"SRM/USDT"},"egldusdt":{"base_unit":"egld","quote_unit":"usdt","low":"46.796","high":"55.0","last":"47.895","type":"SPOT","open":53.0,"volume":"1443.48","sell":"48.101","buy":"47.643","at":1611679416,"name":"EGLD/USDT"},"cosusdt":{"base_unit":"cos","quote_unit":"usdt","low":"0.00748","high":"0.00839","last":"0.00758","type":"SPOT","open":0.0084,"volume":"81351.7","sell":"0.0077","buy":"0.0075","at":1611679416,"name":"COS/USDT"},"nbsusdt":{"base_unit":"nbs","quote_unit":"usdt","low":"0.01308","high":"0.01407","last":"0.01376","type":"SPOT","open":0.01361,"volume":"625190.0","sell":"0.01377","buy":"0.01332","at":1611679416,"name":"NBS/USDT"},"aionusdt":{"base_unit":"aion","quote_unit":"usdt","low":"0.0712","high":"0.0796","last":"0.0721","type":"SPOT","open":0.0786,"volume":"157095.02","sell":"0.0743","buy":"0.0729","at":1611679416,"name":"AION/USDT"},"dotusdt":{"base_unit":"dot","quote_unit":"usdt","low":"16.05","high":"17.85","last":"16.7218","type":"SPOT","open":17.7461,"volume":"24210.48","sell":"16.9","buy":"16.7964","at":1611679416,"name":"DOT/USDT"},"yfiusdt":{"base_unit":"yfi","quote_unit":"usdt","low":"28414.67","high":"31431.82","last":"29470.68","type":"SPOT","open":31269.25,"volume":"8.390332","sell":"29703.44","buy":"29511.18","at":1611679416,"name":"YFI/USDT"},"iotxusdt":{"base_unit":"iotx","quote_unit":"usdt","low":"0.009025","high":"0.009513","last":"0.009324","type":"SPOT","open":0.009603,"volume":"150640.0","sell":"0.0094","buy":"0.009322","at":1611679416,"name":"IOTX/USDT"},"sandusdt":{"base_unit":"sand","quote_unit":"usdt","low":"0.088176","high":"0.105","last":"0.089541","type":"SPOT","open":0.096366,"volume":"39085.0","sell":"0.092226","buy":"0.091002","at":1611679416,"name":"SAND/USDT"},"uniusdt":{"base_unit":"uni","quote_unit":"usdt","low":"10.9617","high":"13.2554","last":"13.122","type":"SPOT","open":11.4313,"volume":"23533.4","sell":"13.287","buy":"13.1303","at":1611679416,"name":"UNI/USDT"},"datausdt":{"base_unit":"data","quote_unit":"usdt","low":"0.05382","high":"0.05922","last":"0.05615","type":"SPOT","open":0.05814,"volume":"38516.0","sell":"0.05681","buy":"0.05581","at":1611679416,"name":"DATA/USDT"},"paxgusdt":{"base_unit":"paxg","quote_unit":"usdt","low":"0.0","high":"0.0","last":"0.0","type":"SPOT","open":"0.0","volume":"0.0","sell":"0.0","buy":"0.0","at":1611679416,"name":"PAXG/USDT"},"creamusdt":{"base_unit":"cream","quote_unit":"usdt","low":"151.45","high":"181.032","last":"163.392","type":"SPOT","open":185.018,"volume":"564.768","sell":"164.409","buy":"161.169","at":1611679416,"name":"CREAM/USDT"},"swrvusdt":{"base_unit":"swrv","quote_unit":"usdt","low":"0.0","high":"0.0","last":"0.0","type":"SPOT","open":"0.0","volume":"0.0","sell":"0.0","buy":"0.0","at":1611679416,"name":"SWRV/USDT"},"umausdt":{"base_unit":"uma","quote_unit":"usdt","low":"10.465","high":"11.476","last":"10.707","type":"SPOT","open":11.363,"volume":"149.268","sell":"10.707","buy":"10.572","at":1611679416,"name":"UMA/USDT"},"diausdt":{"base_unit":"dia","quote_unit":"usdt","low":"0.0","high":"0.0","last":"0.0","type":"SPOT","open":"0.0","volume":"0.0","sell":"0.0","buy":"0.0","at":1611679416,"name":"DIA/USDT"},"ksmusdt":{"base_unit":"ksm","quote_unit":"usdt","low":"0.0","high":"0.0","last":"0.0","type":"SPOT","open":"0.0","volume":"0.0","sell":"0.0","buy":"0.0","at":1611679416,"name":"KSM/USDT"},"yfiiusdt":{"base_unit":"yfii","quote_unit":"usdt","low":"1712.03","high":"1889.59","last":"1747.26","type":"SPOT","open":1887.53,"volume":"111.240023","sell":"1770.0","buy":"1753.19","at":1611679416,"name":"YFII/USDT"},"bzrxusdt":{"base_unit":"bzrx","quote_unit":"usdt","low":"0.0","high":"0.0","last":"0.0","type":"SPOT","open":"0.0","volume":"0.0","sell":"0.0","buy":"0.0","at":1611679416,"name":"BZRX/USDT"},"trbusdt":{"base_unit":"trb","quote_unit":"usdt","low":"0.0","high":"0.0","last":"0.0","type":"SPOT","open":"0.0","volume":"0.0","sell":"0.0","buy":"0.0","at":1611679416,"name":"TRB/USDT"},"adxusdt":{"base_unit":"adx","quote_unit":"usdt","low":"0.4153","high":"0.4507","last":"0.4213","type":"SPOT","open":0.4389,"volume":"6607.0","sell":"0.4214","buy":"0.4171","at":1611679416,"name":"ADX/USDT"},"aaveusdt":{"base_unit":"aave","quote_unit":"usdt","low":"240.213","high":"269.915","last":"264.0","type":"SPOT","open":248.629,"volume":"352.644","sell":"264.4","buy":"262.88","at":1611679416,"name":"AAVE/USDT"},"filusdt":{"base_unit":"fil","quote_unit":"usdt","low":"21.9123","high":"22.8705","last":"21.9196","type":"SPOT","open":22.8929,"volume":"270.87","sell":"22.2479","buy":"21.9527","at":1611679416,"name":"FIL/USDT"},"crvusdt":{"base_unit":"crv","quote_unit":"usdt","low":"1.826","high":"2.205","last":"1.996","type":"SPOT","open":2.1,"volume":"16396.128","sell":"2.024","buy":"1.997","at":1611679416,"name":"CRV/USDT"},"nearusdt":{"base_unit":"near","quote_unit":"usdt","low":"2.2227","high":"2.4719","last":"2.2725","type":"SPOT","open":2.491,"volume":"466.436","sell":"2.2629","buy":"2.2355","at":1611679416,"name":"NEAR/USDT"},"hntusdt":{"base_unit":"hnt","quote_unit":"usdt","low":"1.904","high":"2.228","last":"1.914","type":"SPOT","open":2.077,"volume":"3936.631","sell":"1.956","buy":"1.922","at":1611679416,"name":"HNT/USDT"},"avaxusdt":{"base_unit":"avax","quote_unit":"usdt","low":"11.5","high":"12.6372","last":"11.8395","type":"SPOT","open":12.629,"volume":"833.69","sell":"11.9788","buy":"11.9186","at":1611679416,"name":"AVAX/USDT"},"oxtusdt":{"base_unit":"oxt","quote_unit":"usdt","low":"0.2867","high":"0.3104","last":"0.2868","type":"SPOT","open":0.3104,"volume":"4993.04","sell":"0.2915","buy":"0.2868","at":1611679416,"name":"OXT/USDT"},"dockusdt":{"base_unit":"dock","quote_unit":"usdt","low":"0.022581","high":"0.024798","last":"0.023104","type":"SPOT","open":0.024821,"volume":"626627.0","sell":"0.023411","buy":"0.023197","at":1611679416,"name":"DOCK/USDT"},"duskusdt":{"base_unit":"dusk","quote_unit":"usdt","low":"0.0633","high":"0.0684","last":"0.0633","type":"SPOT","open":0.0698,"volume":"75064.14","sell":"0.0645","buy":"0.0633","at":1611679416,"name":"DUSK/USDT"},"wtcusdt":{"base_unit":"wtc","quote_unit":"usdt","low":"0.3446","high":"0.3779","last":"0.3446","type":"SPOT","open":0.365,"volume":"4740.17","sell":"0.3489","buy":"0.3439","at":1611679416,"name":"WTC/USDT"},"perlusdt":{"base_unit":"perl","quote_unit":"usdt","low":"0.0","high":"0.0","last":"0.0","type":"SPOT","open":"0.0","volume":"0.0","sell":"0.0","buy":"0.0","at":1611679416,"name":"PERL/USDT"},"straxusdt":{"base_unit":"strax","quote_unit":"usdt","low":"0.5069","high":"0.5301","last":"0.5069","type":"SPOT","open":0.5525,"volume":"203.57","sell":"0.5337","buy":"0.5276","at":1611679416,"name":"STRAX/USDT"},"injusdt":{"base_unit":"inj","quote_unit":"usdt","low":"7.6","high":"8.6756","last":"8.2896","type":"SPOT","open":8.6756,"volume":"2767.97","sell":"8.5587","buy":"8.4545","at":1611679416,"name":"INJ/USDT"},"vetusdt":{"base_unit":"vet","quote_unit":"usdt","low":"0.028199","high":"0.031439","last":"0.029011","type":"SPOT","open":0.030947,"volume":"5003857.0","sell":"0.029311","buy":"0.029019","at":1611679416,"name":"VET/USDT"},"mtlusdt":{"base_unit":"mtl","quote_unit":"usdt","low":"0.3989","high":"0.46","last":"0.4186","type":"SPOT","open":0.4053,"volume":"8070.76","sell":"0.4243","buy":"0.418","at":1611679416,"name":"MTL/USDT"},"frontusdt":{"base_unit":"front","quote_unit":"usdt","low":"0.5914","high":"0.7405","last":"0.6101","type":"SPOT","open":0.6871,"volume":"22473.81","sell":"0.6258","buy":"0.6096","at":1611679416,"name":"FRONT/USDT"},"glmusdt":{"base_unit":"glm","quote_unit":"usdt","low":"0.1107","high":"0.1182","last":"0.1107","type":"SPOT","open":0.1204,"volume":"6318.0","sell":"0.1145","buy":"0.1109","at":1611679416,"name":"GLM/USDT"},"sushiusdt":{"base_unit":"sushi","quote_unit":"usdt","low":"6.852","high":"8.349","last":"7.582","type":"SPOT","open":7.97,"volume":"6125.3","sell":"7.655","buy":"7.612","at":1611679416,"name":"SUSHI/USDT"},"ethwrx":{"base_unit":"eth","quote_unit":"wrx","low":"13979.0","high":"15200.0","last":"14112.0","type":"SPOT","open":15130.0,"volume":"29.749","sell":"14346.0","buy":"14291.0","at":1611679416,"name":"ETH/WRX"},"xrpwrx":{"base_unit":"xrp","quote_unit":"wrx","low":"2.82","high":"2.98","last":"2.9","type":"SPOT","open":2.98,"volume":"17885.0","sell":"2.9","buy":"2.86","at":1611679416,"name":"XRP/WRX"},"yfiwrx":{"base_unit":"yfi","quote_unit":"wrx","low":"311582.0","high":"337300.0","last":"322151.0","type":"SPOT","open":337300.0,"volume":"0.329122","sell":"326602.0","buy":"322158.0","at":1611679416,"name":"YFI/WRX"},"bnbwrx":{"base_unit":"bnb","quote_unit":"wrx","low":"433.0","high":"464.0","last":"450.0","type":"SPOT","open":462.0,"volume":"20.46","sell":"449.0","buy":"443.0","at":1611679416,"name":"BNB/WRX"},"trxwrx":{"base_unit":"trx","quote_unit":"wrx","low":"0.3112","high":"0.3319","last":"0.3207","type":"SPOT","open":0.3292,"volume":"227537.0","sell":"0.3209","buy":"0.3182","at":1611679416,"name":"TRX/WRX"},"eoswrx":{"base_unit":"eos","quote_unit":"wrx","low":"27.85","high":"29.25","last":"28.67","type":"SPOT","open":29.25,"volume":"395.25","sell":"28.87","buy":"28.12","at":1611679416,"name":"EOS/WRX"},"ltcwrx":{"base_unit":"ltc","quote_unit":"wrx","low":"1446.0","high":"1535.0","last":"1463.0","type":"SPOT","open":1514.0,"volume":"32.334","sell":"1472.0","buy":"1456.0","at":1611679416,"name":"LTC/WRX"},"linkwrx":{"base_unit":"link","quote_unit":"wrx","low":"247.0","high":"262.0","last":"251.0","type":"SPOT","open":258.0,"volume":"234.98","sell":"248.0","buy":"244.0","at":1611679416,"name":"LINK/WRX"}}